Projekt/gpioemu.v
/* verilator lint_off WIDTH */
/* verilator lint_off UNUSED */
/* verilator lint_off CASEINCOMPLETE */
/* verilator lint_off MULTIDRIVEN */

module gpioemu(
    input             n_reset,
    input  [15:0]     saddress,
    input             srd,
    input             swr,
    input  [31:0]     sdata_in,
    output reg [31:0] sdata_out,
    input  [31:0]     gpio_in,
    input             gpio_latch,
    output [31:0]     gpio_out,
    input             clk,
    output [31:0]     gpio_in_s_insp
);

    // wymagane rejestry wewnętrzne GPIO
    reg [31:0] gpio_in_s;
    reg [31:0] gpio_out_s;

    assign gpio_out = gpio_out_s;
    assign gpio_in_s_insp = gpio_in_s;

    // Rejestry projektowe
    reg [31:0] arg1_h, arg1_l;
    reg [31:0] arg2_h, arg2_l;
    reg [31:0] ctrl_reg;
    reg [31:0] status_reg;
    reg [31:0] res_h, res_l;

    // Automat stanów
    reg [1:0] state;
    localparam S_IDLE  = 2'd0, S_CALC  = 2'd1, S_WRITE = 2'd2, S_DONE  = 2'd3;

    // Zatrzaskiwane argumenty
    reg [63:0] arg1_r;
    reg [63:0] arg2_r;

    wire sign1 = arg1_r[0];
    wire sign2 = arg2_r[0];

    wire [26:0] exp1 = arg1_r[27:1];
    wire [26:0] exp2 = arg2_r[27:1];

    wire [35:0] mant1 = arg1_r[63:28];
    wire [35:0] mant2 = arg2_r[63:28];

    localparam [26:0] BIAS = 27'd67108864; // 2^26

    // Rejestry pomocnicze dla mnożenia
    reg [73:0] prod_reg;
    reg signed [27:0] exp_reg;
    reg sign_reg;
    
    wire signed [27:0] final_exp = exp_reg + (prod_reg[73] ? 1 : 0);
    wire [35:0] final_mant = prod_reg[73] ? prod_reg[72:37] : prod_reg[71:36];

    // Zatrzaśnięcie gpio_in
    always @(posedge gpio_latch or negedge n_reset) begin
        if (!n_reset)
            gpio_in_s <= 32'd0;
        else
            gpio_in_s <= gpio_in;
    end

    // Zapis z procesora (reakcja na zbocze swr)
    always @(posedge swr or negedge n_reset) begin
        if (!n_reset) begin
            arg1_h <= 0; arg1_l <= 0;
            arg2_h <= 0; arg2_l <= 0;
            ctrl_reg <= 0;
        end else begin
            case (saddress)
                16'h0100: arg1_h <= sdata_in;
                16'h0108: arg1_l <= sdata_in;
                16'h00F0: arg2_h <= sdata_in;
                16'h00F8: arg2_l <= sdata_in;
                16'h00D0: ctrl_reg <= sdata_in;
                default: ;
            endcase
        end
    end

    // Automat stanów i obliczenia (reakcja na clk)
    always @(posedge clk or negedge n_reset) begin
        if (!n_reset) begin
            state <= S_IDLE;
            status_reg <= 0;
            res_h <= 0; res_l <= 0;
            arg1_r <= 0;
            arg2_r <= 0;
            prod_reg <= 0;
            exp_reg <= 0;
            sign_reg <= 0;
            gpio_out_s <= 0;
        end else begin
            case (state)
                S_IDLE: begin
                    status_reg <= 0;
                    if (ctrl_reg[0]) begin
                        // Zatrzaśnięcie argumentów
                        arg1_r <= {arg1_h, arg1_l};
                        arg2_r <= {arg2_h, arg2_l};
                        state <= S_CALC;
                    end
                end

                S_CALC: begin
                    status_reg <= 1; // busy
                    // wykrycie zera: E = 0 i M = 0 -> wynik zero
                    if ((exp1 == 0 && mant1 == 0) ||
                        (exp2 == 0 && mant2 == 0)) begin
                        prod_reg <= 0;
                        exp_reg  <= 0;
                        sign_reg <= 0;
                    end else begin
                        prod_reg <= {1'b1, mant1} * {1'b1, mant2};
                        exp_reg  <= $signed({1'b0, exp1}) + $signed({1'b0, exp2}) - $signed({1'b0, BIAS});
                        sign_reg <= sign1 ^ sign2;
                    end
                    state <= S_WRITE;
                end
                
                S_WRITE: begin
                    res_h <= final_mant[35:4];
                    res_l <= { final_mant[3:0], final_exp[26:0], sign_reg };
                    state <= S_DONE;
                end

                S_DONE: begin
                    status_reg <= 2;    // done
                    if (!ctrl_reg[0]) begin // Powrót do IDLE dopiero po wyzerowaniu bitu sterującego
                        status_reg <= 0; // idle
                        state <= S_IDLE;
                    end
                end

            endcase
        end
    end

    // Odczyt dla procesora (układ kombinacyjny)
    always @(*) begin
        case (saddress)
            16'h0100: sdata_out = arg1_h;
            16'h0108: sdata_out = arg1_l;
            16'h00F0: sdata_out = arg2_h;
            16'h00F8: sdata_out = arg2_l;
            16'h00E8: sdata_out = status_reg;
            16'h00D8: sdata_out = res_h;
            16'h00E0: sdata_out = res_l;
            16'h00D0: sdata_out = ctrl_reg;
            default:  sdata_out = 32'd0;
        endcase
    end

endmodule

Projekt/gpioemu_tb.v
module gpioemu_tb;

    
    // SYGNAŁY
    
    reg n_reset, clk, srd, swr, gpio_latch;
    reg [15:0] saddress;
    reg [31:0] sdata_in, gpio_in;

    wire [31:0] sdata_out, gpio_out, gpio_in_s_insp;

    
    // test_module
    
    gpioemu test_module (
        .n_reset(n_reset),
        .saddress(saddress),
        .srd(srd),
        .swr(swr),
        .sdata_in(sdata_in),
        .sdata_out(sdata_out),
        .gpio_in(gpio_in),
        .gpio_latch(gpio_latch),
        .gpio_out(gpio_out),
        .clk(clk),
        .gpio_in_s_insp(gpio_in_s_insp)
    );

    // ZEGAR
    always #5 clk = ~clk;

    // POMOCNICZE
    reg [63:0] result, r1, r2;
    reg [31:0] status;

    localparam [26:0] BIAS = 27'd67108864; // BIAS = 2^(27-1)

    // FORMAT FP:
    // [0]     znak
    // [27:1]  wykładnik z BIAS
    // [63:28] mantysa (bez ukrytej jedynki)
    
    function [63:0] make_fp;
        input        s;
        input [26:0] e;
        input [35:0] m;
        begin
            make_fp = 64'd0;
            make_fp[0]      = s;
            make_fp[27:1]   = e;
            make_fp[63:28]  = m;
        end
    endfunction

    task reset;
        begin
            n_reset = 0; #10;
            n_reset = 1; #10;
        end
    endtask

    task write_arg1(input [63:0] v);
        begin
            saddress = 16'h0100; sdata_in = v[63:32]; swr = 1; #10 swr = 0;
            saddress = 16'h0108; sdata_in = v[31:0];  swr = 1; #10 swr = 0;
        end
    endtask

    task write_arg2(input [63:0] v);
        begin
            saddress = 16'h00F0; sdata_in = v[63:32]; swr = 1; #10 swr = 0;
            saddress = 16'h00F8; sdata_in = v[31:0];  swr = 1; #10 swr = 0;
        end
    endtask

    task start;
        begin
            saddress = 16'h00D0; sdata_in = 32'h1; swr = 1; #10 swr = 0;
            #40; // czas na FSM: CALC -> WRITE -> DONE
        end
    endtask

    task ctrl_reset;
        begin
            saddress = 16'h00D0;
            sdata_in = 32'h0;   // echo 0 > ctrl
            swr = 1; #10 swr = 0;
            #20;               // daj FSM wrócić do IDLE
        end
    endtask


    task read_result(output [63:0] v);
        begin
            saddress = 16'h00D8; srd = 1; #10 srd = 0;
            v[63:32] = sdata_out;
            saddress = 16'h00E0; srd = 1; #10 srd = 0;
            v[31:0]  = sdata_out;
        end
    endtask

    task read_status(output [31:0] v);
        begin
            saddress = 16'h00E8; srd = 1; #10 srd = 0;
            v = sdata_out;
        end
    endtask

    // Wypisywanie pól liczby
    task print_fp(input [63:0] fp);
        begin
            $display("  sign = %0d", fp[0]);
            $display("  exp  = %0d (BIAS %+0d)", fp[27:1], fp[27:1] - BIAS);
            $display("  mant = 0x%h", fp[63:28]);
        end
    endtask

    
    // TESTY
    
    initial begin
        $dumpfile("gpioemu.vcd");
        $dumpvars(0, gpioemu_tb);

        clk = 0;
        srd = 0; swr = 0;
        gpio_latch = 0;
        saddress = 0;
        sdata_in = 0;
        gpio_in = 0;

        // TEST 1: 1.0 * 2.0 = 2.0
        $display("TEST 1 - mnozenie 1.0 * 2.0");
        reset();
        write_arg1(make_fp(0, BIAS,   36'h0)); // 1.0
        write_arg2(make_fp(0, BIAS+1, 36'h0)); // 2.0
        start();
        read_result(result);
        print_fp(result);
        $display("wynik = %h", result);

        // TEST 2: -1.5 * 2.0 = -3.0
        $display("\nTEST 2 - mnozenie -1.5 * 2.0");
        ctrl_reset();
        write_arg1(make_fp(1, BIAS,   36'h80000000)); // -1.5
        write_arg2(make_fp(0, BIAS+1, 36'h0));
        start();
        read_result(result);
        print_fp(result);
        $display("wynik = %h", result);

        // TEST 3: 1.75 * 1.75 = 3.0625 (renormalizacja w górę)
        $display("\nTEST 3 - mnozenie 1.75 * 1.75");
        ctrl_reset();
        write_arg1(make_fp(0, BIAS, 36'hC000000)); // 1.75
        write_arg2(make_fp(0, BIAS, 36'hC000000));
        start();
        read_result(result);
        print_fp(result);
        $display("wynik = %h", result);

        // TEST 4: 1.25 * 1.25 = 1.5625 (bez renormalizacji)
        $display("\nTEST 4 - mnozenie 1.25 * 1.25");
        ctrl_reset();
        write_arg1(make_fp(0, BIAS, 36'h4000000)); // 1.25
        write_arg2(make_fp(0, BIAS, 36'h4000000));
        start();
        read_result(result);
        print_fp(result);
        $display("wynik = %h", result);

        // TEST 5: 2.0 * 4.0 = 8.0
        $display("\nTEST 5 - mnozenie 2.0 * 4.0");
        ctrl_reset();
        write_arg1(make_fp(0, BIAS+1, 36'h0)); // 2.0
        write_arg2(make_fp(0, BIAS+2, 36'h0)); // 4.0
        start();
        read_result(result);
        print_fp(result);
        $display("wynik = %h", result);


        // TEST 6: 0 * 5 = 0
        $display("\nTEST 6 - mnozenie 0 * 5");
        ctrl_reset();
        write_arg1(make_fp(0, 0, 36'h0)); // 0.0
        write_arg2(make_fp(0, BIAS+2, 36'h4000000)); // 5.0
        start();
        read_result(result);
        print_fp(result);
        $display("wynik = %h", result);


        // TEST 7: przemienność
        $display("\nTEST 7 - przemiennosc mnozenia");
        ctrl_reset();
        write_arg1(make_fp(0, BIAS+1, 36'h0)); // 2.0
        write_arg2(make_fp(0, BIAS,   36'h0)); // 1.0
        start();
        read_result(r1);
        print_fp(r1);

        ctrl_reset();
        write_arg1(make_fp(0, BIAS,   36'h0)); // 1.0
        write_arg2(make_fp(0, BIAS+1, 36'h0)); // 2.0
        start();
        read_result(r2);
        print_fp(r2);

        $display("przemiennosc = %s", (r1 == r2) ? "OK" : "BLAD");

        $display("\nWSZYSTKIE TESTY ZAKONCZONE");
        $finish;
    end

endmodule

Projekt/gpioemu.vcd
$date
	Sat May 02 09:42:49 2026
$end
$version
	Icarus Verilog
$end
$timescale
	1s
$end
$scope module gpioemu_tb $end
$var wire 32 ! sdata_out [31:0] $end
$var wire 32 " gpio_out [31:0] $end
$var wire 32 # gpio_in_s_insp [31:0] $end
$var parameter 27 $ BIAS $end
$var reg 1 % clk $end
$var reg 32 & gpio_in [31:0] $end
$var reg 1 ' gpio_latch $end
$var reg 1 ( n_reset $end
$var reg 64 ) r1 [63:0] $end
$var reg 64 * r2 [63:0] $end
$var reg 64 + result [63:0] $end
$var reg 16 , saddress [15:0] $end
$var reg 32 - sdata_in [31:0] $end
$var reg 1 . srd $end
$var reg 1 / swr $end
$scope function make_fp $end
$var reg 27 0 e [26:0] $end
$var reg 36 1 m [35:0] $end
$var reg 1 2 s $end
$upscope $end
$scope module test_module $end
$var wire 1 % clk $end
$var wire 32 3 gpio_in [31:0] $end
$var wire 32 4 gpio_in_s_insp [31:0] $end
$var wire 1 ' gpio_latch $end
$var wire 32 5 gpio_out [31:0] $end
$var wire 1 ( n_reset $end
$var wire 16 6 saddress [15:0] $end
$var wire 32 7 sdata_in [31:0] $end
$var wire 1 . srd $end
$var wire 1 / swr $end
$var wire 1 8 sign2 $end
$var wire 1 9 sign1 $end
$var wire 36 : mant2 [35:0] $end
$var wire 36 ; mant1 [35:0] $end
$var wire 36 < final_mant [35:0] $end
$var wire 28 = final_exp [27:0] $end
$var wire 27 > exp2 [26:0] $end
$var wire 27 ? exp1 [26:0] $end
$var parameter 27 @ BIAS $end
$var parameter 2 A S_CALC $end
$var parameter 2 B S_DONE $end
$var parameter 2 C S_IDLE $end
$var parameter 2 D S_WRITE $end
$var reg 32 E arg1_h [31:0] $end
$var reg 32 F arg1_l [31:0] $end
$var reg 64 G arg1_r [63:0] $end
$var reg 32 H arg2_h [31:0] $end
$var reg 32 I arg2_l [31:0] $end
$var reg 64 J arg2_r [63:0] $end
$var reg 32 K ctrl_reg [31:0] $end
$var reg 28 L exp_reg [27:0] $end
$var reg 32 M gpio_in_s [31:0] $end
$var reg 32 N gpio_out_s [31:0] $end
$var reg 74 O prod_reg [73:0] $end
$var reg 32 P res_h [31:0] $end
$var reg 32 Q res_l [31:0] $end
$var reg 32 R sdata_out [31:0] $end
$var reg 1 S sign_reg $end
$var reg 2 T state [1:0] $end
$var reg 32 U status_reg [31:0] $end
$upscope $end
$scope task ctrl_reset $end
$upscope $end
$scope task print_fp $end
$var reg 64 V fp [63:0] $end
$upscope $end
$scope task read_result $end
$var reg 64 W v [63:0] $end
$upscope $end
$scope task read_status $end
$var reg 32 X v [31:0] $end
$upscope $end
$scope task reset $end
$upscope $end
$scope task start $end
$upscope $end
$scope task write_arg1 $end
$var reg 64 Y v [63:0] $end
$upscope $end
$scope task write_arg2 $end
$var reg 64 Z v [63:0] $end
$upscope $end
$upscope $end
$enddefinitions $end
$comment Show the parameter values. $end
$dumpall
b10 D
b0 C
b11 B
b1 A
b100000000000000000000000000 @
b100000000000000000000000000 $
$end
#0
$dumpvars
bx Z
bx Y
bx X
bx W
bx V
b0 U
b0 T
0S
b0 R
b0 Q
b0 P
b0 O
b0 N
b0 M
b0 L
b0 K
b0 J
b0 I
b0 H
b0 G
b0 F
b0 E
b0 ?
b0 >
b0 =
b0 <
b0 ;
b0 :
09
08
b0 7
b0 6
b0 5
b0 4
b0 3
x2
bx 1
bx 0
0/
0.
b0 -
b0 ,
bx +
bx *
bx )
0(
0'
b0 &
0%
b0 #
b0 "
b0 !
$end
#5
1%
#10
0%
1(
#15
1%
#20
0%
1/
b100000000 ,
b100000000 6
b1000000000000000000000000000 Y
02
b100000000000000000000000000 0
b0 1
#25
1%
#30
b1000000000000000000000000000 !
b1000000000000000000000000000 R
b1000000000000000000000000000 F
0%
b1000000000000000000000000000 -
b1000000000000000000000000000 7
b100001000 ,
b100001000 6
1/
#35
1%
#40
b0 !
b0 R
0%
b0 -
b0 7
b11110000 ,
b11110000 6
b1000000000000000000000000010 Z
b100000000000000000000000001 0
1/
#45
1%
#50
b1000000000000000000000000010 !
b1000000000000000000000000010 R
b1000000000000000000000000010 I
0%
b1000000000000000000000000010 -
b1000000000000000000000000010 7
b11111000 ,
b11111000 6
1/
#55
1%
#60
b1 K
b1 !
b1 R
0%
b1 -
b1 7
b11010000 ,
b11010000 6
1/
#65
b100000000000000000000000001 >
b100000000000000000000000000 ?
b1 T
b1000000000000000000000000010 J
b1000000000000000000000000000 G
1%
#70
0%
0/
#75
b10 T
b100000000000000000000000001 =
b100000000000000000000000001 L
b1000000000000000000000000000000000000000000000000000000000000000000000000 O
b1 U
1%
#80
0%
#85
b11 T
b1000000000000000000000000010 Q
1%
#90
0%
#95
b10 U
1%
#100
0%
#105
1%
#110
b0 !
b0 R
0%
1.
b11011000 ,
b11011000 6
#115
1%
#120
b1000000000000000000000000010 !
b1000000000000000000000000010 R
0%
b11100000 ,
b11100000 6
b0xxxxxxxxxxxxxxxxxxxxxxxxxxxxxxxx W
1.
#125
1%
#130
b0 K
b0 !
b0 R
0%
1/
b0 -
b0 7
b11010000 ,
b11010000 6
b1000000000000000000000000010 V
b1000000000000000000000000010 +
b1000000000000000000000000010 W
0.
#135
b0 T
b0 U
1%
#140
0%
0/
#145
1%
#150
0%
#155
1%
#160
b1000000000000000000000000000 !
b1000000000000000000000000000 R
b1000000000000000000000000000 E
0%
1/
b1000000000000000000000000000 -
b1000000000000000000000000000 7
b100000000 ,
b100000000 6
b100000000000000000000000000000001000000000000000000000000001 Y
12
b100000000000000000000000000 0
b10000000000000000000000000000000 1
#165
1%
#170
b1000000000000000000000000001 !
b1000000000000000000000000001 R
b1000000000000000000000000001 F
0%
b1000000000000000000000000001 -
b1000000000000000000000000001 7
b100001000 ,
b100001000 6
1/
#175
1%
#180
b0 !
b0 R
0%
b0 -
b0 7
b11110000 ,
b11110000 6
02
b100000000000000000000000001 0
b0 1
1/
#185
1%
#190
b1000000000000000000000000010 !
b1000000000000000000000000010 R
0%
b1000000000000000000000000010 -
b1000000000000000000000000010 7
b11111000 ,
b11111000 6
1/
#195
1%
#200
b1 K
b1 !
b1 R
0%
b1 -
b1 7
b11010000 ,
b11010000 6
1/
#205
19
b10000000000000000000000000000000 ;
b1 T
b100000000000000000000000000000001000000000000000000000000001 G
1%
#210
0%
0/
#215
b10000000000000000000000000000000 <
b10 T
1S
b1000010000000000000000000000000000000000000000000000000000000000000000000 O
b1 U
1%
#220
0%
#225
b11 T
b1000000000000000000000000011 Q
b1000000000000000000000000000 P
1%
#230
0%
#235
b10 U
1%
#240
0%
#245
1%
#250
b1000000000000000000000000000 !
b1000000000000000000000000000 R
0%
1.
b11011000 ,
b11011000 6
#255
1%
#260
b1000000000000000000000000011 !
b1000000000000000000000000011 R
0%
b11100000 ,
b11100000 6
b100000000000000000000000000000001000000000000000000000000010 W
1.
#265
1%
#270
b0 K
b0 !
b0 R
0%
1/
b0 -
b0 7
b11010000 ,
b11010000 6
b100000000000000000000000000000001000000000000000000000000011 V
b100000000000000000000000000000001000000000000000000000000011 +
b100000000000000000000000000000001000000000000000000000000011 W
0.
#275
b0 T
b0 U
1%
#280
0%
0/
#285
1%
#290
0%
#295
1%
#300
b110000000000000000000000 E
b110000000000000000000000 !
b110000000000000000000000 R
0%
1/
b110000000000000000000000 -
b110000000000000000000000 7
b100000000 ,
b100000000 6
b11000000000000000000000000001000000000000000000000000000 Y
b100000000000000000000000000 0
b1100000000000000000000000000 1
#305
1%
#310
b1000000000000000000000000000 F
b1000000000000000000000000000 !
b1000000000000000000000000000 R
0%
b1000000000000000000000000000 -
b1000000000000000000000000000 7
b100001000 ,
b100001000 6
1/
#315
1%
#320
b110000000000000000000000 H
b110000000000000000000000 !
b110000000000000000000000 R
0%
b110000000000000000000000 -
b110000000000000000000000 7
b11110000 ,
b11110000 6
b11000000000000000000000000001000000000000000000000000000 Z
1/
#325
1%
#330
b1000000000000000000000000000 I
b1000000000000000000000000000 !
b1000000000000000000000000000 R
0%
b1000000000000000000000000000 -
b1000000000000000000000000000 7
b11111000 ,
b11111000 6
1/
#335
1%
#340
b1 K
b1 !
b1 R
0%
b1 -
b1 7
b11010000 ,
b11010000 6
1/
#345
b100000000000000000000000000 >
b1100000000000000000000000000 :
09
b1100000000000000000000000000 ;
b1 T
b11000000000000000000000000001000000000000000000000000000 J
b11000000000000000000000000001000000000000000000000000000 G
1%
#350
0%
0/
#355
b11000000010010000000000000000 <
b10 T
0S
b100000000000000000000000000 =
b100000000000000000000000000 L
b1000000011000000010010000000000000000000000000000000000000000000000000000 O
b1 U
1%
#360
0%
#365
b11 T
b1000000000000000000000000000 Q
b1100000001001000000000000 P
1%
#370
0%
#375
b10 U
1%
#380
0%
#385
1%
#390
b1100000001001000000000000 !
b1100000001001000000000000 R
0%
1.
b11011000 ,
b11011000 6
#395
1%
#400
b1000000000000000000000000000 !
b1000000000000000000000000000 R
0%
b11100000 ,
b11100000 6
b110000000100100000000000000001000000000000000000000000011 W
1.
#405
1%
#410
b0 K
b0 !
b0 R
0%
1/
b0 -
b0 7
b11010000 ,
b11010000 6
b110000000100100000000000000001000000000000000000000000000 V
b110000000100100000000000000001000000000000000000000000000 +
b110000000100100000000000000001000000000000000000000000000 W
0.
#415
b0 T
b0 U
1%
#420
0%
0/
#425
1%
#430
0%
#435
1%
#440
b10000000000000000000000 E
b10000000000000000000000 !
b10000000000000000000000 R
0%
1/
b10000000000000000000000 -
b10000000000000000000000 7
b100000000 ,
b100000000 6
b1000000000000000000000000001000000000000000000000000000 Y
b100000000000000000000000000 1
#445
1%
#450
b1000000000000000000000000000 !
b1000000000000000000000000000 R
0%
b1000000000000000000000000000 -
b1000000000000000000000000000 7
b100001000 ,
b100001000 6
1/
#455
1%
#460
b10000000000000000000000 H
b10000000000000000000000 !
b10000000000000000000000 R
0%
b10000000000000000000000 -
b10000000000000000000000 7
b11110000 ,
b11110000 6
b1000000000000000000000000001000000000000000000000000000 Z
1/
#465
1%
#470
b1000000000000000000000000000 !
b1000000000000000000000000000 R
0%
b1000000000000000000000000000 -
b1000000000000000000000000000 7
b11111000 ,
b11111000 6
1/
#475
1%
#480
b1 K
b1 !
b1 R
0%
b1 -
b1 7
b11010000 ,
b11010000 6
1/
#485
b100000000000000000000000000 :
b100000000000000000000000000 ;
b1 T
b1000000000000000000000000001000000000000000000000000000 J
b1000000000000000000000000001000000000000000000000000000 G
1%
#490
0%
0/
#495
b1000000000010000000000000000 <
b10 T
b1000000001000000000010000000000000000000000000000000000000000000000000000 O
b1 U
1%
#500
0%
#505
b11 T
b100000000001000000000000 P
1%
#510
0%
#515
b10 U
1%
#520
0%
#525
1%
#530
b100000000001000000000000 !
b100000000001000000000000 R
0%
1.
b11011000 ,
b11011000 6
#535
1%
#540
b1000000000000000000000000000 !
b1000000000000000000000000000 R
0%
b11100000 ,
b11100000 6
b10000000000100000000000000001000000000000000000000000000 W
1.
#545
1%
#550
b0 K
b0 !
b0 R
0%
1/
b0 -
b0 7
b11010000 ,
b11010000 6
b10000000000100000000000000001000000000000000000000000000 V
b10000000000100000000000000001000000000000000000000000000 +
0.
#555
b0 T
b0 U
1%
#560
0%
0/
#565
1%
#570
0%
#575
1%
#580
b0 E
b0 !
b0 R
0%
1/
b100000000 ,
b100000000 6
b1000000000000000000000000010 Y
b100000000000000000000000001 0
b0 1
#585
1%
#590
b1000000000000000000000000010 F
b1000000000000000000000000010 !
b1000000000000000000000000010 R
0%
b1000000000000000000000000010 -
b1000000000000000000000000010 7
b100001000 ,
b100001000 6
1/
#595
1%
#600
b0 H
b0 !
b0 R
0%
b0 -
b0 7
b11110000 ,
b11110000 6
b1000000000000000000000000100 Z
b100000000000000000000000010 0
1/
#605
1%
#610
b1000000000000000000000000100 I
b1000000000000000000000000100 !
b1000000000000000000000000100 R
0%
b1000000000000000000000000100 -
b1000000000000000000000000100 7
b11111000 ,
b11111000 6
1/
#615
1%
#620
b1 K
b1 !
b1 R
0%
b1 -
b1 7
b11010000 ,
b11010000 6
1/
#625
b100000000000000000000000010 >
b0 :
b100000000000000000000000001 ?
b0 ;
b1 T
b1000000000000000000000000100 J
b1000000000000000000000000010 G
1%
#630
0%
0/
#635
b0 <
b10 T
b100000000000000000000000011 =
b100000000000000000000000011 L
b1000000000000000000000000000000000000000000000000000000000000000000000000 O
b1 U
1%
#640
0%
#645
b11 T
b1000000000000000000000000110 Q
b0 P
1%
#650
0%
#655
b10 U
1%
#660
0%
#665
1%
#670
b0 !
b0 R
0%
1.
b11011000 ,
b11011000 6
#675
1%
#680
b1000000000000000000000000110 !
b1000000000000000000000000110 R
0%
b11100000 ,
b11100000 6
b1000000000000000000000000000 W
1.
#685
1%
#690
b0 K
b0 !
b0 R
0%
1/
b0 -
b0 7
b11010000 ,
b11010000 6
b1000000000000000000000000110 V
b1000000000000000000000000110 +
b1000000000000000000000000110 W
0.
#695
b0 T
b0 U
1%
#700
0%
0/
#705
1%
#710
0%
#715
1%
#720
0%
1/
b100000000 ,
b100000000 6
b0 Y
b0 0
#725
1%
#730
b0 F
b0 !
b0 R
0%
b100001000 ,
b100001000 6
1/
#735
1%
#740
b10000000000000000000000 !
b10000000000000000000000 R
b10000000000000000000000 H
0%
b10000000000000000000000 -
b10000000000000000000000 7
b11110000 ,
b11110000 6
b1000000000000000000000000001000000000000000000000000100 Z
b100000000000000000000000010 0
b100000000000000000000000000 1
1/
#745
1%
#750
b1000000000000000000000000100 !
b1000000000000000000000000100 R
0%
b1000000000000000000000000100 -
b1000000000000000000000000100 7
b11111000 ,
b11111000 6
1/
#755
1%
#760
b1 K
b1 !
b1 R
0%
b1 -
b1 7
b11010000 ,
b11010000 6
1/
#765
b100000000000000000000000000 :
b0 ?
b1 T
b1000000000000000000000000001000000000000000000000000100 J
b0 G
1%
#770
0%
0/
#775
b10 T
b0 =
b0 L
b0 O
b1 U
1%
#780
0%
#785
b11 T
b0 Q
1%
#790
0%
#795
b10 U
1%
#800
0%
#805
1%
#810
b0 !
b0 R
0%
1.
b11011000 ,
b11011000 6
#815
1%
#820
0%
b11100000 ,
b11100000 6
1.
#825
1%
#830
b0 K
b0 !
b0 R
0%
1/
b0 -
b0 7
b11010000 ,
b11010000 6
b0 V
b0 +
b0 W
0.
#835
b0 T
b0 U
1%
#840
0%
0/
#845
1%
#850
0%
#855
1%
#860
0%
1/
b100000000 ,
b100000000 6
b1000000000000000000000000010 Y
b100000000000000000000000001 0
b0 1
#865
1%
#870
b1000000000000000000000000010 !
b1000000000000000000000000010 R
b1000000000000000000000000010 F
0%
b1000000000000000000000000010 -
b1000000000000000000000000010 7
b100001000 ,
b100001000 6
1/
#875
1%
#880
b0 H
b0 !
b0 R
0%
b0 -
b0 7
b11110000 ,
b11110000 6
b1000000000000000000000000000 Z
b100000000000000000000000000 0
1/
#885
1%
#890
b1000000000000000000000000000 I
b1000000000000000000000000000 !
b1000000000000000000000000000 R
0%
b1000000000000000000000000000 -
b1000000000000000000000000000 7
b11111000 ,
b11111000 6
1/
#895
1%
#900
b1 K
b1 !
b1 R
0%
b1 -
b1 7
b11010000 ,
b11010000 6
1/
#905
b100000000000000000000000000 >
b0 :
b100000000000000000000000001 ?
b1 T
b1000000000000000000000000000 J
b1000000000000000000000000010 G
1%
#910
0%
0/
#915
b10 T
b100000000000000000000000001 =
b100000000000000000000000001 L
b1000000000000000000000000000000000000000000000000000000000000000000000000 O
b1 U
1%
#920
0%
#925
b11 T
b1000000000000000000000000010 Q
1%
#930
0%
#935
b10 U
1%
#940
0%
#945
1%
#950
b0 !
b0 R
0%
1.
b11011000 ,
b11011000 6
#955
1%
#960
b1000000000000000000000000010 !
b1000000000000000000000000010 R
0%
b11100000 ,
b11100000 6
1.
#965
1%
#970
b0 K
b0 !
b0 R
0%
1/
b0 -
b0 7
b11010000 ,
b11010000 6
b1000000000000000000000000010 V
b1000000000000000000000000010 )
b1000000000000000000000000010 W
0.
#975
b0 T
b0 U
1%
#980
0%
0/
#985
1%
#990
0%
#995
1%
#1000
0%
1/
b100000000 ,
b100000000 6
b1000000000000000000000000000 Y
#1005
1%
#1010
b1000000000000000000000000000 F
b1000000000000000000000000000 !
b1000000000000000000000000000 R
0%
b1000000000000000000000000000 -
b1000000000000000000000000000 7
b100001000 ,
b100001000 6
1/
#1015
1%
#1020
b0 !
b0 R
0%
b0 -
b0 7
b11110000 ,
b11110000 6
b1000000000000000000000000010 Z
b100000000000000000000000001 0
1/
#1025
1%
#1030
b1000000000000000000000000010 I
b1000000000000000000000000010 !
b1000000000000000000000000010 R
0%
b1000000000000000000000000010 -
b1000000000000000000000000010 7
b11111000 ,
b11111000 6
1/
#1035
1%
#1040
b1 K
b1 !
b1 R
0%
b1 -
b1 7
b11010000 ,
b11010000 6
1/
#1045
b100000000000000000000000001 >
b100000000000000000000000000 ?
b1 T
b1000000000000000000000000010 J
b1000000000000000000000000000 G
1%
#1050
0%
0/
#1055
b10 T
b1 U
1%
#1060
0%
#1065
b11 T
1%
#1070
0%
#1075
b10 U
1%
#1080
0%
#1085
1%
#1090
b0 !
b0 R
0%
1.
b11011000 ,
b11011000 6
#1095
1%
#1100
b1000000000000000000000000010 !
b1000000000000000000000000010 R
0%
b11100000 ,
b11100000 6
1.
#1105
1%
#1110
0%
b1000000000000000000000000010 *
0.
