Projekt/gpioemu.v
// gpioemu.v
/* verilator lint_off WIDTH */
/* verilator lint_off UNUSED */
/* verilator lint_off CASEINCOMPLETE */
/* verilator lint_off MULTIDRIVEN */

module gpioemu(
    input            n_reset,
    input  [15:0]    saddress,
    input            srd,
    input            swr,
    input  [31:0]    sdata_in,
    output reg [31:0] sdata_out,
    input  [31:0]    gpio_in,
    input            gpio_latch,
    output [31:0]    gpio_out,
    input            clk,
    output [31:0]    gpio_in_s_insp
);

    // WYMAGANE REJESTRY WEWNĘTRZNE
    reg [31:0] gpio_in_s;
    reg [31:0] gpio_out_s;
    reg [31:0] sdata_in_s;

    // Rejestry projektowe
    reg [31:0] arg1_h, arg1_l;
    reg [31:0] arg2_h, arg2_l;
    reg [31:0] ctrl_reg;
    reg [31:0] status_reg;
    reg [31:0] res_h, res_l;

    // Automat stanów
    reg [1:0] state;
    localparam S_IDLE = 2'd0, S_CALC = 2'd1, S_DONE = 2'd2;

    // Rejestry pomocnicze dla mnożenia
    reg [73:0] prod_reg;
    reg signed [27:0] exp_reg;   // signed – do bezpiecznego odejmowania BIAS
    reg sign_reg;

    // BIAS = 2^26 = 67108864
    localparam [26:0] BIAS = 27'd67108864;

    // Wyciągnięcie pól z argumentów (zgodnie z formatem)
    wire [35:0] mant1 = {arg1_h, arg1_l[31:28]};
    wire [35:0] mant2 = {arg2_h, arg2_l[31:28]};
    wire [26:0] exp1  = arg1_l[27:1];
    wire [26:0] exp2  = arg2_l[27:1];
    wire sign1 = arg1_l[0];
    wire sign2 = arg2_l[0];

    assign gpio_out = gpio_out_s;
    assign gpio_in_s_insp = gpio_in_s;
    always @(*) sdata_in_s = sdata_in;

    // Zatrzaśnięcie gpio_in
    always @(posedge gpio_latch or negedge n_reset) begin
        if (!n_reset) gpio_in_s <= 0;
        else gpio_in_s <= gpio_in;
    end

    // Zapis z procesora (reakcja na zbocze swr)
    always @(posedge swr or negedge n_reset) begin
        if (!n_reset) begin
            arg1_h <= 0; arg1_l <= 0;
            arg2_h <= 0; arg2_l <= 0;
            ctrl_reg <= 0;
        end else begin
            case (saddress)
                16'h0100: arg1_h <= sdata_in_s;
                16'h0108: arg1_l <= sdata_in_s;
                16'h00F0: arg2_h <= sdata_in_s;
                16'h00F8: arg2_l <= sdata_in_s;
                16'h00D0: ctrl_reg <= sdata_in_s;
                default: ;
            endcase
        end
    end

    // Automat stanów i obliczenia (reakcja na clk)
    always @(posedge clk or negedge n_reset) begin
        if (!n_reset) begin
            state <= S_IDLE;
            status_reg <= 0;
            res_h <= 0; res_l <= 0;
            gpio_out_s <= 0;
            prod_reg <= 0;
            exp_reg <= 0;
            sign_reg <= 0;
        end else begin
            case (state)
                S_IDLE: begin
                    if (ctrl_reg[0]) begin
                        // Wykryto sygnał startu
                        if ((exp1 == 0 && mant1 == 0) || (exp2 == 0 && mant2 == 0)) begin
                            // Przynajmniej jeden argument zerowy -> wynik zero
                            res_h <= 0;
                            res_l <= 0;
                            status_reg <= 2; // done
                            state <= S_DONE;
                        end else begin
                            // Mnożenie 1.mant1 * 1.mant2
                            prod_reg <= {1'b1, mant1} * {1'b1, mant2};
                            exp_reg  <= $signed({1'b0, exp1}) + $signed({1'b0, exp2}) - $signed({1'b0, BIAS});
                            sign_reg <= sign1 ^ sign2;
                            status_reg <= 1; // busy
                            state <= S_CALC;
                        end
                    end else begin
                        status_reg <= 0; // idle
                    end
                end

                S_CALC: begin
                    // Jeden cykl na ustabilizowanie się wyniku mnożenia
                    state <= S_DONE;
                end

                S_DONE: begin
                    // Normalizacja i zapis wyniku
                    wire signed [27:0] final_exp_signed = exp_reg + (prod_reg[73] ? 28'd1 : 28'd0);
                    if (final_exp_signed < 0 || final_exp_signed > 28'h7FFFFFF) begin
                        // Przekroczenie zakresu -> zero
                        res_h <= 0;
                        res_l <= 0;
                    end else begin
                        wire [26:0] new_exp = final_exp_signed[26:0];
                        wire [35:0] new_mant = prod_reg[73] ? prod_reg[72:37] : prod_reg[71:36];
                        res_h <= new_mant[35:4];
                        res_l <= {new_mant[3:0], new_exp, sign_reg};
                    end
                    status_reg <= 2; // done
                    // Powrót do IDLE dopiero po wyzerowaniu bitu sterującego
                    if (!ctrl_reg[0]) begin
                        state <= S_IDLE;
                    end
                end

                default: state <= S_IDLE;
            endcase
        end
    end

    // Odczyt dla procesora (układ kombinacyjny)
    always @(*) begin
        case (saddress)
            16'h0100: sdata_out = arg1_h;
            16'h0108: sdata_out = arg1_l;
            16'h00F0: sdata_out = arg2_h;
            16'h00F8: sdata_out = arg2_l;
            16'h00E8: sdata_out = status_reg;
            16'h00D8: sdata_out = res_h;
            16'h00E0: sdata_out = res_l;
            16'h00D0: sdata_out = ctrl_reg;
            default:  sdata_out = 0;
        endcase
    end

endmodule

Projekt/gpioemu_tb.v
module gpioemu_tb;
    // Sygnały sterujące
    reg n_reset, clk, srd, swr, gpio_latch;
    reg [15:0] saddress;
    reg [31:0] sdata_in, gpio_in;
    
    // Sygnały wyjściowe z modułu
    wire [31:0] sdata_out, gpio_out, gpio_in_s_insp;
    
    // Instancja testowanego modułu
    gpioemu test_module (
        .n_reset(n_reset),
        .saddress(saddress),
        .srd(srd),
        .swr(swr),
        .sdata_in(sdata_in),
        .sdata_out(sdata_out),
        .gpio_in(gpio_in),
        .gpio_latch(gpio_latch),
        .gpio_out(gpio_out),
        .clk(clk),
        .gpio_in_s_insp(gpio_in_s_insp)
    );

    // Generowanie zegara (okres 10 jednostek)
    always #5 clk = ~clk;

    // BIAS dla 27-bitowego wykładnika: 2^(27-1) = 2^26 = 67108864
    localparam [26:0] BIAS = 27'd67108864;

    // Zmienne pomocnicze
    reg [63:0] result_val, result1, result2;
    reg [31:0] status_val;

    //----------------------------------------------------------------------
    // Funkcja pomocnicza do tworzenia liczby 64-bitowej w formacie:
    // [0]=S (znak), [27:1]=E (eksponenta z BIAS), [63:28]=M (mantysa)
    //----------------------------------------------------------------------
    function [63:0] make_fp;
        input        s;          // znak (0=dodatni, 1=ujemny)
        input [26:0] e;          // wykładnik (już z BIAS-em)
        input [35:0] m;          // mantysa (bez ukrytej jedynki)
        begin
            make_fp[0]      = s;
            make_fp[27:1]   = e;
            make_fp[63:28]  = m;
        end
    endfunction

    //----------------------------------------------------------------------
    // Funkcja pomocnicza do czytelnego wyświetlania liczby FP
    //----------------------------------------------------------------------
    task display_fp;
        input [63:0] fp;
        input [255:0] label;     // opcjonalna etykieta
        reg [35:0] mant;
        reg [26:0] exp;
        reg        sign;
        begin
            sign = fp[0];
            exp  = fp[27:1];
            mant = fp[63:28];
            
            if (label != "")
                $write("%s: ", label);
            else
                $write("FP: ");
                
            if (exp == 27'd0 && mant == 36'd0) begin
                $display("0.0 (S=%b, E=0, M=0)", sign);
            end else begin
                $display("S=%b, E=%0d (BIAS+%0d), M=0x%h",
                sign, exp, exp - BIAS, mant);
            end
        end
    endtask

    //----------------------------------------------------------------------
    // Pomocnicze taski do często powtarzanych operacji
    //----------------------------------------------------------------------
    task reset_module;
        begin
            #10 n_reset = 0;
            #10 n_reset = 1;
            #10;
        end
    endtask

    task write_arg1;
        input [63:0] value;
        begin
            #10 saddress = 16'h0100; sdata_in = value[63:32]; swr = 1; #10 swr = 0;
            #10 saddress = 16'h0108; sdata_in = value[31:0];  swr = 1; #10 swr = 0;
        end
    endtask

    task write_arg2;
        input [63:0] value;
        begin
            #10 saddress = 16'h00F0; sdata_in = value[63:32]; swr = 1; #10 swr = 0;
            #10 saddress = 16'h00F8; sdata_in = value[31:0];  swr = 1; #10 swr = 0;
        end
    endtask

    task start_operation;
        begin
            #10 saddress = 16'h00D0; sdata_in = 32'h00000001; swr = 1; #10 swr = 0;
            #50; // Oczekiwanie na zakonczenie
        end
    endtask

    task read_result;
        output [63:0] result;
        begin
            #10 saddress = 16'h00D8; srd = 1; #10 srd = 0;
            result[63:32] = sdata_out;
            #10 saddress = 16'h00E0; srd = 1; #10 srd = 0;
            result[31:0] = sdata_out;
        end
    endtask

    task read_status;
        output [31:0] stat;
        begin
            #10 saddress = 16'h00E8; srd = 1; #10 srd = 0;
            stat = sdata_out;
        end
    endtask

    //======================================================================
    // GŁÓWNY BLOK TESTOWY
    //======================================================================
    initial begin
        $dumpfile("gpioemu.vcd");
        $dumpvars(0, gpioemu_tb);

        // Inicjalizacja
        clk = 0; n_reset = 1;
        srd = 0; swr = 0;
        gpio_latch = 0;
        saddress = 16'h0;
        sdata_in = 32'h0;
        gpio_in = 32'h0;
        result_val = 64'h0;
        status_val = 32'h0;
        result1 = 64'h0;
        result2 = 64'h0;

        // Reset początkowy
        reset_module();

        // ================================================================
        // TEST 1: 1.0 * 2.0 = 2.0
        // ================================================================
        $display("\n=== TEST 1: 1.0 * 2.0 = 2.0 ===");
        $display("  arg1 (1.0): S=0, E=BIAS, M=0");
        $display("  arg2 (2.0): S=0, E=BIAS+1, M=0");
        write_arg1(make_fp(1'b0, BIAS, 36'h0));
        write_arg2(make_fp(1'b0, BIAS+1, 36'h0));
        start_operation();
        read_status(status_val);
        $display("  Status: %h (oczekiwane: 00000002)", status_val);
        read_result(result_val);
        display_fp(result_val, "  Wynik ");
        $display("  Oczekiwany: S=0, E=BIAS+1, M=0");
        $display("  TEST 1: %s",
        (result_val[0] == 0 && result_val[27:1] == BIAS+1 && result_val[63:28] == 0) 
        ? "ZALICZONY" : "BLAD");

        // ================================================================
        // TEST 2: -1.5 * 2.0 = -3.0
        // ================================================================
        $display("\n=== TEST 2: -1.5 * 2.0 = -3.0 ===");
        $display("  arg1 (-1.5): S=1, E=BIAS, M=0.5");
        $display("  arg2 (2.0):  S=0, E=BIAS+1, M=0");
        reset_module();
        write_arg1(make_fp(1'b1, BIAS, 36'h80000000));
        write_arg2(make_fp(1'b0, BIAS+1, 36'h0));
        start_operation();
        read_result(result_val);
        display_fp(result_val, "  Wynik ");
        $display("  Oczekiwany: S=1, E=BIAS+1, M=0.5");
        $display("  TEST 2: %s",
        (result_val[0] == 1 && result_val[63:28] == 36'h80000000)
        ? "ZALICZONY" : "BLAD");

        // ================================================================
        // TEST 3: Neutralność – odczyt spod nieprawidłowego adresu
        // ================================================================
        $display("\n=== TEST 3: Neutralnosc magistrali ===");
        #10 saddress = 16'hFFFF; srd = 1; #10 srd = 0;
        $display("  Odczyt spod FFFF: %h (oczekiwane: 00000000)", sdata_out);
        $display("  TEST 3: %s", (sdata_out == 32'h0) ? "ZALICZONY" : "BLAD");

        // ================================================================
        // TEST 4: Brak uruchomienia przy control = 0
        // ================================================================
        $display("\n=== TEST 4: Control = 0 nie uruchamia ===");
        reset_module();
        write_arg1(make_fp(1'b0, BIAS, 36'h0));
        write_arg2(make_fp(1'b0, BIAS+1, 36'h0));
        #10 saddress = 16'h00D0; sdata_in = 32'h00000000; swr = 1; #10 swr = 0;
        #20;
        read_status(status_val);
        $display("  Status: %h (oczekiwane: 00000000 - IDLE)", status_val);
        $display("  TEST 4: %s", (status_val == 32'h0) ? "ZALICZONY" : "BLAD");

        // ================================================================
        // TEST 5: GPIO – zatrzaśnięcie i podgląd
        // ================================================================
        $display("\n=== TEST 5: Zatrzasniecie GPIO ===");
        #10 gpio_in = 32'hDEADBEEF;
        #10 gpio_latch = 1; #10 gpio_latch = 0;
        #10;
        $display("  gpio_in_s_insp: %h (oczekiwane: DEADBEEF)", gpio_in_s_insp);
        $display("  TEST 5: %s", (gpio_in_s_insp == 32'hDEADBEEF) ? "ZALICZONY" : "BLAD");

        // ================================================================
        // TEST 6: Reset globalny czyści rejestry
        // ================================================================
        $display("\n=== TEST 6: Reset globalny ===");
        reset_module();
        #10 saddress = 16'h0100; srd = 1; #10 srd = 0;
        $display("  arg1_h po resecie: %h (oczekiwane: 0)", sdata_out);
        $display("  TEST 6: %s", (sdata_out == 32'h0) ? "ZALICZONY" : "BLAD");

        // ================================================================
        // TEST 7: Mnożenie przez zero (0.0 * 5.0 = 0.0)
        // ================================================================
        $display("\n=== TEST 7: Mnożenie przez zero (0.0 * 5.0 = 0.0) ===");
        $display("  arg1 (0.0): E=0, M=0 (specjalny wzorzec zera)");
        $display("  arg2 (5.0): S=0, E=BIAS+2, M=0.25");
        reset_module();
        write_arg1(make_fp(1'b0, 27'd0, 36'h0));
        write_arg2(make_fp(1'b0, BIAS+2, 36'h4000000));
        start_operation();
        read_result(result_val);
        display_fp(result_val, "  Wynik ");
        $display("  Oczekiwany: 0.0");
        $display("  TEST 7: %s",
        (result_val == 64'h0) ? "ZALICZONY" : "BLAD");

        // ================================================================
        // TEST 8: -2.0 * -3.0 = +6.0
        // ================================================================
        $display("\n=== TEST 8: -2.0 * -3.0 = +6.0 ===");
        $display("  arg1 (-2.0): S=1, E=BIAS+1, M=0");
        $display("  arg2 (-3.0): S=1, E=BIAS+1, M=0.5");
        reset_module();
        write_arg1(make_fp(1'b1, BIAS+1, 36'h0));
        write_arg2(make_fp(1'b1, BIAS+1, 36'h80000000));
        start_operation();
        read_result(result_val);
        display_fp(result_val, "  Wynik ");
        $display("  Oczekiwany: S=0, E=BIAS+2, M=0.5");
        $display("  TEST 8: %s",
        (result_val[0] == 0 && result_val[63:28] == 36'h80000000)
        ? "ZALICZONY" : "BLAD");

        // ================================================================
        // TEST 9: Odczyt przed zakonczeniem operacji
        // ================================================================
        $display("\n=== TEST 9: Odczyt przed zakonczeniem ===");
        reset_module();
        write_arg1(make_fp(1'b0, BIAS, 36'h0));
        write_arg2(make_fp(1'b0, BIAS+1, 36'h0));
        
        // Uruchom, ale NIE czekaj długo
        #10 saddress = 16'h00D0; sdata_in = 32'h1; swr = 1; #10 swr = 0;
        #10; // Tylko jeden cykl
        
        read_status(status_val);
        $display("  Status po 1 cyklu: %h (0=IDLE, 1=BUSY, 2=DONE)", status_val);
        
        read_result(result_val);
        display_fp(result_val, "  Przedwczesny odczyt");
        
        // Poczekaj na zakonczenie
        #50;
        read_status(status_val);
        $display("  Status po odczekaniu: %h (oczekiwane: 2=DONE)", status_val);
        read_result(result_val);
        display_fp(result_val, "  Wynik po odczekaniu");
        $display("  TEST 9: %s",
        (result_val[0] == 0 && result_val[27:1] == BIAS+1 && result_val[63:28] == 0)
        ? "ZALICZONY" : "BLAD");

        // ================================================================
        // TEST 10: Podwójny start
        // ================================================================
        $display("\n=== TEST 10: Podwójny start ===");
        reset_module();
        write_arg1(make_fp(1'b0, BIAS, 36'h0));
        write_arg2(make_fp(1'b0, BIAS+1, 36'h0));
        
        // Pierwszy start
        #10 saddress = 16'h00D0; sdata_in = 32'h1; swr = 1; #10 swr = 0;
        #10;
        
        // Drugi start (przed zakonczeniem)
        #10 saddress = 16'h00D0; sdata_in = 32'h1; swr = 1; #10 swr = 0;
        #50;
        read_result(result_val);
        display_fp(result_val, "  Wynik po podwojnym starcie");
        $display("  TEST 10: %s",
        (result_val[0] == 0 && result_val[27:1] == BIAS+1 && result_val[63:28] == 0)
        ? "ZALICZONY" : "BLAD");

        // ================================================================
        // TEST 11: Nieprawidłowe wartości control
        // ================================================================
        $display("\n=== TEST 11: Nieprawidlowe wartosci control ===");
        reset_module();
        write_arg1(make_fp(1'b0, BIAS, 36'h0));
        write_arg2(make_fp(1'b0, BIAS+1, 36'h0));
        
        // control = 0xFF
        #10 saddress = 16'h00D0; sdata_in = 32'h000000FF; swr = 1; #10 swr = 0;
        #30;
        read_status(status_val);
        $display("  Status po control=0xFF: %h (oczekiwane: 0=IDLE)", status_val);
        $display("  TEST 11a: %s", (status_val == 32'h0) ? "ZALICZONY" : "BLAD");
        
        // control = 2
        #10 saddress = 16'h00D0; sdata_in = 32'h00000002; swr = 1; #10 swr = 0;
        #30;
        read_status(status_val);
        $display("  Status po control=2: %h (oczekiwane: 0=IDLE)", status_val);
        $display("  TEST 11b: %s", (status_val == 32'h0) ? "ZALICZONY" : "BLAD");

        // ================================================================
        // TEST 12: Częściowy zapis argumentów
        // ================================================================
        $display("\n=== TEST 12: Czesciowy zapis argumentow ===");
        reset_module();
        
        // Zapisz tylko górną część arg1
        #10 saddress = 16'h0100; sdata_in = 32'h80000000; swr = 1; #10 swr = 0;
        
        // Dolna część powinna być 0 (z resetu)
        #10 saddress = 16'h0108; srd = 1; #10 srd = 0;
        $display("  arg1_l po czesciowym zapisie: %h (oczekiwane: 00000000)", sdata_out);
        $display("  TEST 12: %s", (sdata_out == 32'h0) ? "ZALICZONY" : "BLAD");

        // ================================================================
        // TEST 13: Przemienność mnożenia (a*b == b*a)
        // ================================================================
        $display("\n=== TEST 13: Przemiennosc mnozenia ===");
        
        // 2.0 * 1.0
        reset_module();
        write_arg1(make_fp(1'b0, BIAS+1, 36'h0));  // 2.0
        write_arg2(make_fp(1'b0, BIAS, 36'h0));    // 1.0
        start_operation();
        read_result(result1);
        display_fp(result1, "  2.0*1.0");
        
        // 1.0 * 2.0
        reset_module();
        write_arg1(make_fp(1'b0, BIAS, 36'h0));    // 1.0
        write_arg2(make_fp(1'b0, BIAS+1, 36'h0));  // 2.0
        start_operation();
        read_result(result2);
        display_fp(result2, "  1.0*2.0");
        
        if (result1 == result2) begin
            $display("  Przemiennosc: OK");
            $display("  TEST 13: ZALICZONY");
        end else begin
            $display("  Przemiennosc: BLAD! (%h != %h)", result1, result2);
            $display("  TEST 13: BLAD");
        end

        // ================================================================
        // TEST 14: Próba zapisu do rejestru tylko do odczytu (status)
        // ================================================================
        $display("\n=== TEST 14: Zapis do rejestru status (read-only) ===");
        reset_module();
        #10 saddress = 16'h00E8; sdata_in = 32'hFFFFFFFF; swr = 1; #10 swr = 0;
        #10 saddress = 16'h00E8; srd = 1; #10 srd = 0;
        $display("  Status po próbie zapisu: %h (oczekiwane: 0)", sdata_out);
        $display("  TEST 14: %s", (sdata_out == 32'h0) ? "ZALICZONY" : "BLAD");

        // ================================================================
        // TEST 15: Wielokrotne mnożenie bez resetu
        // ================================================================
        $display("\n=== TEST 15: Wielokrotne mnozenie ===");
        reset_module();
        
        // Pierwsza operacja: 1.0 * 2.0 = 2.0
        write_arg1(make_fp(1'b0, BIAS, 36'h0));
        write_arg2(make_fp(1'b0, BIAS+1, 36'h0));
        start_operation();
        read_result(result1);
        display_fp(result1, "  Operacja 1 (1.0*2.0)");
        
        // Druga operacja: 2.0 * 4.0 = 8.0
        write_arg1(make_fp(1'b0, BIAS+1, 36'h0));  // 2.0
        write_arg2(make_fp(1'b0, BIAS+2, 36'h0));  // 4.0
        start_operation();
        read_result(result2);
        display_fp(result2, "  Operacja 2 (2.0*4.0)");
        $display("  Oczekiwany: S=0, E=BIAS+3, M=0");
        $display("  TEST 15: %s",
        (result2[0] == 0 && result2[27:1] == BIAS+3 && result2[63:28] == 0) 
        ? "ZALICZONY" : "BLAD");

        // Koniec symulacji
        #100;
        $display("\n===========================================");
        $display("=== WSZYSTKIE TESTY ZAKONCZONE ===");
        $display("===========================================\n");
        $finish;
    end

    // Monitor komunikatów (uproszczony)
    initial begin
        $monitor("Czas=%0t | Adr=%h | swr=%b srd=%b | data_in=%h | data_out=%h",
        $time, saddress, swr, srd, sdata_in, sdata_out);
    end
endmodule

Projekt/gpioemu.vcd
$date
	Fri May 01 17:15:09 2026
$end
$version
	Icarus Verilog
$end
$timescale
	1s
$end
$scope module gpioemu_tb $end
$var wire 32 ! sdata_out [31:0] $end
$var wire 32 " gpio_out [31:0] $end
$var wire 32 # gpio_in_s_insp [31:0] $end
$var parameter 27 $ BIAS $end
$var reg 1 % clk $end
$var reg 32 & gpio_in [31:0] $end
$var reg 1 ' gpio_latch $end
$var reg 1 ( n_reset $end
$var reg 64 ) result1 [63:0] $end
$var reg 64 * result2 [63:0] $end
$var reg 64 + result_val [63:0] $end
$var reg 16 , saddress [15:0] $end
$var reg 32 - sdata_in [31:0] $end
$var reg 1 . srd $end
$var reg 32 / status_val [31:0] $end
$var reg 1 0 swr $end
$scope function make_fp $end
$var reg 27 1 e [26:0] $end
$var reg 36 2 m [35:0] $end
$var reg 1 3 s $end
$upscope $end
$scope module test_module $end
$var wire 1 % clk $end
$var wire 32 4 gpio_in [31:0] $end
$var wire 32 5 gpio_in_s_insp [31:0] $end
$var wire 1 ' gpio_latch $end
$var wire 32 6 gpio_out [31:0] $end
$var wire 1 ( n_reset $end
$var wire 16 7 saddress [15:0] $end
$var wire 32 8 sdata_in [31:0] $end
$var wire 1 . srd $end
$var wire 1 0 swr $end
$var wire 1 9 sign2 $end
$var wire 1 : sign1 $end
$var wire 36 ; new_mant [35:0] $end
$var wire 27 < new_exp [26:0] $end
$var wire 36 = mant2 [35:0] $end
$var wire 36 > mant1 [35:0] $end
$var wire 28 ? final_exp_signed [27:0] $end
$var wire 27 @ exp2 [26:0] $end
$var wire 27 A exp1 [26:0] $end
$var parameter 27 B BIAS $end
$var parameter 2 C S_CALC $end
$var parameter 2 D S_DONE $end
$var parameter 2 E S_IDLE $end
$var reg 32 F arg1_h [31:0] $end
$var reg 32 G arg1_l [31:0] $end
$var reg 32 H arg2_h [31:0] $end
$var reg 32 I arg2_l [31:0] $end
$var reg 32 J ctrl_reg [31:0] $end
$var reg 28 K exp_reg [27:0] $end
$var reg 32 L gpio_in_s [31:0] $end
$var reg 32 M gpio_out_s [31:0] $end
$var reg 74 N prod_reg [73:0] $end
$var reg 32 O res_h [31:0] $end
$var reg 32 P res_l [31:0] $end
$var reg 32 Q sdata_in_s [31:0] $end
$var reg 32 R sdata_out [31:0] $end
$var reg 1 S sign_reg $end
$var reg 2 T state [1:0] $end
$var reg 32 U status_reg [31:0] $end
$upscope $end
$scope task display_fp $end
$var reg 27 V exp [26:0] $end
$var reg 64 W fp [63:0] $end
$var reg 256 X label [255:0] $end
$var reg 36 Y mant [35:0] $end
$var reg 1 Z sign $end
$upscope $end
$scope task read_result $end
$var reg 64 [ result [63:0] $end
$upscope $end
$scope task read_status $end
$var reg 32 \ stat [31:0] $end
$upscope $end
$scope task reset_module $end
$upscope $end
$scope task start_operation $end
$upscope $end
$scope task write_arg1 $end
$var reg 64 ] value [63:0] $end
$upscope $end
$scope task write_arg2 $end
$var reg 64 ^ value [63:0] $end
$upscope $end
$upscope $end
$enddefinitions $end
$comment Show the parameter values. $end
$dumpall
b0 E
b10 D
b1 C
b100000000000000000000000000 B
b100000000000000000000000000 $
$end
#0
$dumpvars
bx ^
bx ]
bx \
bx [
xZ
bx Y
bx X
bx W
bx V
bx U
bx T
xS
b0 R
b0 Q
bx P
bx O
bx N
bx M
bx L
bx K
bx J
bx I
bx H
bx G
bx F
bx A
bx @
bx ?
bx >
bx =
bx <
bx ;
x:
x9
b0 8
b0 7
bx 6
bx 5
b0 4
x3
bx 2
bx 1
00
b0 /
0.
b0 -
b0 ,
b0 +
b0 *
b0 )
1(
0'
b0 &
0%
bx #
bx "
b0 !
$end
#5
b0 T
1%
#10
b0 <
b0 ?
b0 ;
b0 @
09
b0 A
0:
0S
b0 K
b0 N
b0 "
b0 6
b0 M
b0 P
b0 O
b0 U
b0 J
b0 I
b0 =
b0 H
b0 G
b0 >
b0 F
b0 #
b0 5
b0 L
0%
0(
#15
1%
#20
0%
1(
#25
1%
#30
0%
b1000000000000000000000000000 ]
03
b100000000000000000000000000 1
b0 2
#35
1%
#40
0%
10
b100000000 ,
b100000000 7
#45
1%
#50
0%
00
#55
1%
#60
b1000000000000000000000000000 !
b1000000000000000000000000000 R
b100000000000000000000000000 A
b1000000000000000000000000000 G
b1000000000000000000000000000 Q
0%
10
b1000000000000000000000000000 -
b1000000000000000000000000000 8
b100001000 ,
b100001000 7
#65
1%
#70
0%
b1000000000000000000000000010 ^
b100000000000000000000000001 1
00
#75
1%
#80
b0 Q
b0 !
b0 R
0%
10
b0 -
b0 8
b11110000 ,
b11110000 7
#85
1%
#90
0%
00
#95
1%
#100
b1000000000000000000000000010 !
b1000000000000000000000000010 R
b100000000000000000000000001 @
b1000000000000000000000000010 I
b1000000000000000000000000010 Q
0%
10
b1000000000000000000000000010 -
b1000000000000000000000000010 8
b11111000 ,
b11111000 7
#105
1%
#110
0%
00
#115
1%
#120
b1 J
b1 Q
b1 !
b1 R
0%
10
b1 -
b1 8
b11010000 ,
b11010000 7
#125
b100000000000000000000000001 <
b1 T
b1 U
b100000000000000000000000001 ?
b100000000000000000000000001 K
b1000000000000000000000000000000000000000000000000000000000000000000000000 N
1%
#130
0%
00
#135
b10 T
1%
#140
0%
#145
b10 U
b1000000000000000000000000010 P
1%
#150
0%
#155
1%
#160
0%
#165
1%
#170
0%
#175
1%
#180
0%
#185
1%
#190
b10 !
b10 R
0%
1.
b11101000 ,
b11101000 7
#195
1%
#200
0%
b10 /
b10 \
0.
#205
1%
#210
b0 !
b0 R
0%
1.
b11011000 ,
b11011000 7
#215
1%
#220
0%
b0xxxxxxxxxxxxxxxxxxxxxxxxxxxxxxxx [
0.
#225
1%
#230
b1000000000000000000000000010 !
b1000000000000000000000000010 R
0%
1.
b11100000 ,
b11100000 7
#235
1%
#240
0%
b0 Y
b100000000000000000000000001 V
0Z
b10000000100000010101110111100101101110011010010110101100100000 X
b1000000000000000000000000010 W
b1000000000000000000000000010 +
b1000000000000000000000000010 [
0.
#245
1%
#250
b0 <
b0 @
b0 !
b0 R
b0 A
b0 ?
b0 K
b0 N
b0 P
b0 U
b0 T
b0 J
b0 I
b0 G
0%
0(
#255
1%
#260
0%
1(
#265
1%
#270
0%
b100000000000000000000000000000001000000000000000000000000001 ]
13
b100000000000000000000000000 1
b10000000000000000000000000000000 2
#275
1%
#280
b1000000000000000000000000000 !
b1000000000000000000000000000 R
b10000000000000000000000000000000 >
b1000000000000000000000000000 F
b1000000000000000000000000000 Q
0%
10
b1000000000000000000000000000 -
b1000000000000000000000000000 8
b100000000 ,
b100000000 7
#285
1%
#290
0%
00
#295
1%
#300
b100000000000000000000000000 A
1:
b1000000000000000000000000001 G
b1000000000000000000000000001 Q
b1000000000000000000000000001 !
b1000000000000000000000000001 R
0%
10
b1000000000000000000000000001 -
b1000000000000000000000000001 8
b100001000 ,
b100001000 7
#305
1%
#310
0%
03
b100000000000000000000000001 1
b0 2
00
#315
1%
#320
b0 Q
b0 !
b0 R
0%
10
b0 -
b0 8
b11110000 ,
b11110000 7
#325
1%
#330
0%
00
#335
1%
#340
b1000000000000000000000000010 !
b1000000000000000000000000010 R
b100000000000000000000000001 @
b1000000000000000000000000010 I
b1000000000000000000000000010 Q
0%
10
b1000000000000000000000000010 -
b1000000000000000000000000010 8
b11111000 ,
b11111000 7
#345
1%
#350
0%
00
#355
1%
#360
b1 J
b1 Q
b1 !
b1 R
0%
10
b1 -
b1 8
b11010000 ,
b11010000 7
#365
b10000000000000000000000000000000 ;
b100000000000000000000000001 <
b1 T
b1 U
1S
b100000000000000000000000001 ?
b100000000000000000000000001 K
b1000010000000000000000000000000000000000000000000000000000000000000000000 N
1%
#370
0%
00
#375
b10 T
1%
#380
0%
#385
b10 U
b1000000000000000000000000011 P
b1000000000000000000000000000 O
1%
#390
0%
#395
1%
#400
0%
#405
1%
#410
0%
#415
1%
#420
0%
#425
1%
#430
b1000000000000000000000000000 !
b1000000000000000000000000000 R
0%
1.
b11011000 ,
b11011000 7
#435
1%
#440
0%
b100000000000000000000000000000001000000000000000000000000010 [
0.
#445
1%
#450
b1000000000000000000000000011 !
b1000000000000000000000000011 R
0%
1.
b11100000 ,
b11100000 7
#455
1%
#460
0%
b10000000000000000000000000000000 Y
1Z
b100000000000000000000000000000001000000000000000000000000011 W
b100000000000000000000000000000001000000000000000000000000011 +
b100000000000000000000000000000001000000000000000000000000011 [
0.
#465
1%
#470
b0 ;
b0 <
b0 @
b0 A
0:
b0 !
b0 R
0S
b0 ?
b0 K
b0 N
b0 P
b0 O
b0 U
b0 T
b0 J
b0 I
b0 G
b0 >
b0 F
0%
0(
#475
1%
#480
0%
1(
#485
1%
#490
0%
b11000000000000000000000000001000000000000000000000000000 ]
b100000000000000000000000000 1
b1100000000000000000000000000 2
#495
1%
#500
b110000000000000000000000 !
b110000000000000000000000 R
b1100000000000000000000000000 >
b110000000000000000000000 F
b110000000000000000000000 Q
0%
10
b110000000000000000000000 -
b110000000000000000000000 8
b100000000 ,
b100000000 7
#505
1%
#510
0%
00
#515
1%
#520
b100000000000000000000000000 A
b1000000000000000000000000000 G
b1000000000000000000000000000 Q
b1000000000000000000000000000 !
b1000000000000000000000000000 R
0%
10
b1000000000000000000000000000 -
b1000000000000000000000000000 8
b100001000 ,
b100001000 7
#525
1%
#530
0%
b11000000000000000000000000001000000000000000000000000000 ^
00
#535
1%
#540
b1100000000000000000000000000 =
b110000000000000000000000 H
b110000000000000000000000 Q
b110000000000000000000000 !
b110000000000000000000000 R
0%
10
b110000000000000000000000 -
b110000000000000000000000 8
b11110000 ,
b11110000 7
#545
1%
#550
0%
00
#555
1%
#560
b100000000000000000000000000 @
b1000000000000000000000000000 I
b1000000000000000000000000000 Q
b1000000000000000000000000000 !
b1000000000000000000000000000 R
0%
10
b1000000000000000000000000000 -
b1000000000000000000000000000 8
b11111000 ,
b11111000 7
#565
1%
#570
0%
00
#575
1%
#580
b1 J
b1 Q
b1 !
b1 R
0%
10
b1 -
b1 8
b11010000 ,
b11010000 7
#585
b11000000010010000000000000000 ;
b100000000000000000000000000 <
b1 T
b1 U
b100000000000000000000000000 ?
b100000000000000000000000000 K
b1000000011000000010010000000000000000000000000000000000000000000000000000 N
1%
#590
0%
00
#595
b10 T
1%
#600
0%
#605
b10 U
b1000000000000000000000000000 P
b1100000001001000000000000 O
1%
#610
0%
#615
1%
#620
0%
#625
1%
#630
0%
#635
1%
#640
0%
#645
1%
#650
b1100000001001000000000000 !
b1100000001001000000000000 R
0%
1.
b11011000 ,
b11011000 7
#655
1%
#660
0%
b110000000100100000000000000001000000000000000000000000011 [
0.
#665
1%
