Projekt/gpioemu.v
/* verilator lint_off UNUSED */
/* verilator lint_off UNDRIVEN */
/* verilator lint_off MULTIDRIVEN */
/* verilator lint_off COMBDLY */

module gpioemu(
    input           n_reset,
    input  [15:0]   saddress,
    input           srd,
    input           swr,
    input  [31:0]   sdata_in,
    output reg [31:0] sdata_out,
    input  [31:0]   gpio_in,
    input           gpio_latch,
    output [31:0]   gpio_out,
    input           clk,
    output [31:0]   gpio_in_s_insp
);

    //BUFOROWANIE MAGISTRALI / GPIO (KONTRAKT SYKOM)
    reg [31:0] gpio_in_s   /* verilator public_flat_rw */;
    reg [31:0] gpio_out_s  /* verilator public_flat_rw */;
    reg [31:0] sdata_in_s  /* verilator public_flat_rw */;

    assign gpio_out       = gpio_out_s;
    assign gpio_in_s_insp = gpio_in_s;

    always @(*) begin
        sdata_in_s = sdata_in;
    end

    always @(posedge gpio_latch or negedge n_reset) begin
        if (!n_reset)
            gpio_in_s <= 32'h0;
        else
            gpio_in_s <= gpio_in;
    end

    //REJESTRY DANYCH FP
    reg [63:0] arg1;
    reg [63:0] arg2;
    reg [63:0] result;

    //REJESTRY STERUJĄCE I STATUS
    reg        ena;              // start / ack
    reg [31:0] status;           // 0=idle, 1=busy, 2=done

    // FSM
    reg [1:0] state;

    localparam IDLE = 2'd0;
    localparam CALC = 2'd1;
    localparam DONE = 2'd2;

    localparam [26:0] BIAS = 27'd67108864;

    wire arg1_is_zero = (arg1[27:1] == 0) && (arg1[63:28] == 0);
    wire arg2_is_zero = (arg2[27:1] == 0) && (arg2[63:28] == 0);

    wire [73:0] mant1_ext = arg1_is_zero ? 74'd0 : {37'd0, 1'b1, arg1[63:28]};
    wire [73:0] mant2_ext = arg2_is_zero ? 74'd0 : {37'd0, 1'b1, arg2[63:28]};

    reg        sign_r;
    reg [27:0] exp_sum;
    reg [73:0] mant_prod;

    //ZAPIS Z CPU — ZDARZENIOWO (posedge swr)
    always @(posedge swr or negedge n_reset) begin
        if (!n_reset) begin
            arg1 <= 64'h0;
            arg2 <= 64'h0;
            ena  <= 1'b0;
        end else begin
            case (saddress)
                16'h0100: arg1[63:32] <= sdata_in_s;
                16'h0108: arg1[31:0]  <= sdata_in_s;
                16'h00F0: arg2[63:32] <= sdata_in_s;
                16'h00F8: arg2[31:0]  <= sdata_in_s;
                16'h00D0: ena         <= sdata_in_s[0];
                default: ;
            endcase
        end
    end

    // FSM + OBLICZENIA (clk)
    always @(posedge clk or negedge n_reset) begin
        if (!n_reset) begin
            state  <= IDLE;
            status <= 32'h0;
            result <= 64'h0;
        end else begin
            case (state)
                IDLE: begin
                    status <= 32'h0;
                    if (ena)
                        state <= CALC;
                end

                CALC: begin
                    status    <= 32'h1;   // BUSY

                    mant_prod <= mant1_ext * mant2_ext;
                    exp_sum   <= {1'b0, arg1[27:1]} +
                                 {1'b0, arg2[27:1]} -
                                 {1'b0, BIAS};
                    sign_r    <= arg1[0] ^ arg2[0];

                    /* ==== ZAPIS WYNIKU (TYLKO RAZ!) ==== */
                    if (arg1_is_zero || arg2_is_zero)
                        result <= 64'h0;
                    else begin
                        result[0] <= sign_r;
                        if (mant_prod[73]) begin
                            result[27:1]  <= exp_sum[26:0] + 1;
                            result[63:28] <= mant_prod[72:37];
                        end else begin
                            result[27:1]  <= exp_sum[26:0];
                            result[63:28] <= mant_prod[71:36];
                        end
                    end

                    state <= DONE;
                end

                DONE: begin
                    status <= 32'h2;   // DONE
                    if (!ena)
                        state <= IDLE; // ACK od software
                end

                default: begin
                    state  <= IDLE;
                    status <= 32'h0;
                end
            endcase
        end
    end

    //ODCZYT Z CPU — ZDARZENIOWO (posedge srd)
    always @(posedge srd or negedge n_reset) begin
        if (!n_reset)
            sdata_out <= 32'h0;
        else begin
            case (saddress)
                16'h0100: sdata_out <= arg1[63:32];
                16'h0108: sdata_out <= arg1[31:0];
                16'h00F0: sdata_out <= arg2[63:32];
                16'h00F8: sdata_out <= arg2[31:0];
                16'h00D0: sdata_out <= {31'b0, ena};
                16'h00E8: sdata_out <= status;
                16'h00D8: sdata_out <= result[63:32];
                16'h00E0: sdata_out <= result[31:0];
                default:  sdata_out <= 32'h0;
            endcase
        end
    end

endmodule

Projekt/gpioemu_tb.v
module gpioemu_tb;
    // Sygnały sterujące
    reg n_reset, clk, srd, swr, gpio_latch;
    reg [15:0] saddress;
    reg [31:0] sdata_in, gpio_in;
    
    // Sygnały wyjściowe z modułu
    wire [31:0] sdata_out, gpio_out, gpio_in_s_insp;
    
    // Instancja testowanego modułu
    gpioemu test_module (
        .n_reset(n_reset),
        .saddress(saddress),
        .srd(srd),
        .swr(swr),
        .sdata_in(sdata_in),
        .sdata_out(sdata_out),
        .gpio_in(gpio_in),
        .gpio_latch(gpio_latch),
        .gpio_out(gpio_out),
        .clk(clk),
        .gpio_in_s_insp(gpio_in_s_insp)
    );

    // Generowanie zegara (okres 10 jednostek)
    always #5 clk = ~clk;

    // BIAS dla 27-bitowego wykładnika: 2^(27-1) = 2^26 = 67108864
    localparam [26:0] BIAS = 27'd67108864;

    // Zmienne pomocnicze
    reg [63:0] result_val, result1, result2;
    reg [31:0] status_val;

    //----------------------------------------------------------------------
    // Funkcja pomocnicza do tworzenia liczby 64-bitowej w formacie:
    // [0]=S (znak), [27:1]=E (eksponenta z BIAS), [63:28]=M (mantysa)
    //----------------------------------------------------------------------
    function [63:0] make_fp;
        input        s;          // znak (0=dodatni, 1=ujemny)
        input [26:0] e;          // wykładnik (już z BIAS-em)
        input [35:0] m;          // mantysa (bez ukrytej jedynki)
        begin
            make_fp[0]      = s;
            make_fp[27:1]   = e;
            make_fp[63:28]  = m;
        end
    endfunction

    //----------------------------------------------------------------------
    // Funkcja pomocnicza do czytelnego wyświetlania liczby FP
    //----------------------------------------------------------------------
    task display_fp;
        input [63:0] fp;
        input [255:0] label;     // opcjonalna etykieta
        reg [35:0] mant;
        reg [26:0] exp;
        reg        sign;
        begin
            sign = fp[0];
            exp  = fp[27:1];
            mant = fp[63:28];
            
            if (label != "")
                $write("%s: ", label);
            else
                $write("FP: ");
                
            if (exp == 27'd0 && mant == 36'd0) begin
                $display("0.0 (S=%b, E=0, M=0)", sign);
            end else begin
                $display("S=%b, E=%0d (BIAS+%0d), M=0x%h",
                sign, exp, exp - BIAS, mant);
            end
        end
    endtask

    //----------------------------------------------------------------------
    // Pomocnicze taski do często powtarzanych operacji
    //----------------------------------------------------------------------
    task reset_module;
        begin
            #10 n_reset = 0;
            #10 n_reset = 1;
            #10;
        end
    endtask

    task write_arg1;
        input [63:0] value;
        begin
            #10 saddress = 16'h0100; sdata_in = value[63:32]; swr = 1; #10 swr = 0;
            #10 saddress = 16'h0108; sdata_in = value[31:0];  swr = 1; #10 swr = 0;
        end
    endtask

    task write_arg2;
        input [63:0] value;
        begin
            #10 saddress = 16'h00F0; sdata_in = value[63:32]; swr = 1; #10 swr = 0;
            #10 saddress = 16'h00F8; sdata_in = value[31:0];  swr = 1; #10 swr = 0;
        end
    endtask

    task start_operation;
        begin
            #10 saddress = 16'h00D0; sdata_in = 32'h00000001; swr = 1; #10 swr = 0;
            #50; // Oczekiwanie na zakonczenie
        end
    endtask

    task read_result;
        output [63:0] result;
        begin
            #10 saddress = 16'h00D8; srd = 1; #10 srd = 0;
            result[63:32] = sdata_out;
            #10 saddress = 16'h00E0; srd = 1; #10 srd = 0;
            result[31:0] = sdata_out;
        end
    endtask

    task read_status;
        output [31:0] stat;
        begin
            #10 saddress = 16'h00E8; srd = 1; #10 srd = 0;
            stat = sdata_out;
        end
    endtask

    //======================================================================
    // GŁÓWNY BLOK TESTOWY
    //======================================================================
    initial begin
        $dumpfile("gpioemu.vcd");
        $dumpvars(0, gpioemu_tb);

        // Inicjalizacja
        clk = 0; n_reset = 1;
        srd = 0; swr = 0;
        gpio_latch = 0;
        saddress = 16'h0;
        sdata_in = 32'h0;
        gpio_in = 32'h0;
        result_val = 64'h0;
        status_val = 32'h0;
        result1 = 64'h0;
        result2 = 64'h0;

        // Reset początkowy
        reset_module();

        // ================================================================
        // TEST 1: 1.0 * 2.0 = 2.0
        // ================================================================
        $display("\n=== TEST 1: 1.0 * 2.0 = 2.0 ===");
        $display("  arg1 (1.0): S=0, E=BIAS, M=0");
        $display("  arg2 (2.0): S=0, E=BIAS+1, M=0");
        write_arg1(make_fp(1'b0, BIAS, 36'h0));
        write_arg2(make_fp(1'b0, BIAS+1, 36'h0));
        start_operation();
        read_status(status_val);
        $display("  Status: %h (oczekiwane: 00000002)", status_val);
        read_result(result_val);
        display_fp(result_val, "  Wynik ");
        $display("  Oczekiwany: S=0, E=BIAS+1, M=0");
        $display("  TEST 1: %s",
        (result_val[0] == 0 && result_val[27:1] == BIAS+1 && result_val[63:28] == 0) 
        ? "ZALICZONY" : "BLAD");

        // ================================================================
        // TEST 2: -1.5 * 2.0 = -3.0
        // ================================================================
        $display("\n=== TEST 2: -1.5 * 2.0 = -3.0 ===");
        $display("  arg1 (-1.5): S=1, E=BIAS, M=0.5");
        $display("  arg2 (2.0):  S=0, E=BIAS+1, M=0");
        reset_module();
        write_arg1(make_fp(1'b1, BIAS, 36'h80000000));
        write_arg2(make_fp(1'b0, BIAS+1, 36'h0));
        start_operation();
        read_result(result_val);
        display_fp(result_val, "  Wynik ");
        $display("  Oczekiwany: S=1, E=BIAS+1, M=0.5");
        $display("  TEST 2: %s",
        (result_val[0] == 1 && result_val[63:28] == 36'h80000000)
        ? "ZALICZONY" : "BLAD");

        // ================================================================
        // TEST 3: Neutralność – odczyt spod nieprawidłowego adresu
        // ================================================================
        $display("\n=== TEST 3: Neutralnosc magistrali ===");
        #10 saddress = 16'hFFFF; srd = 1; #10 srd = 0;
        $display("  Odczyt spod FFFF: %h (oczekiwane: 00000000)", sdata_out);
        $display("  TEST 3: %s", (sdata_out == 32'h0) ? "ZALICZONY" : "BLAD");

        // ================================================================
        // TEST 4: Brak uruchomienia przy control = 0
        // ================================================================
        $display("\n=== TEST 4: Control = 0 nie uruchamia ===");
        reset_module();
        write_arg1(make_fp(1'b0, BIAS, 36'h0));
        write_arg2(make_fp(1'b0, BIAS+1, 36'h0));
        #10 saddress = 16'h00D0; sdata_in = 32'h00000000; swr = 1; #10 swr = 0;
        #20;
        read_status(status_val);
        $display("  Status: %h (oczekiwane: 00000000 - IDLE)", status_val);
        $display("  TEST 4: %s", (status_val == 32'h0) ? "ZALICZONY" : "BLAD");

        // ================================================================
        // TEST 5: GPIO – zatrzaśnięcie i podgląd
        // ================================================================
        $display("\n=== TEST 5: Zatrzasniecie GPIO ===");
        #10 gpio_in = 32'hDEADBEEF;
        #10 gpio_latch = 1; #10 gpio_latch = 0;
        #10;
        $display("  gpio_in_s_insp: %h (oczekiwane: DEADBEEF)", gpio_in_s_insp);
        $display("  TEST 5: %s", (gpio_in_s_insp == 32'hDEADBEEF) ? "ZALICZONY" : "BLAD");

        // ================================================================
        // TEST 6: Reset globalny czyści rejestry
        // ================================================================
        $display("\n=== TEST 6: Reset globalny ===");
        reset_module();
        #10 saddress = 16'h0100; srd = 1; #10 srd = 0;
        $display("  arg1_h po resecie: %h (oczekiwane: 0)", sdata_out);
        $display("  TEST 6: %s", (sdata_out == 32'h0) ? "ZALICZONY" : "BLAD");

        // ================================================================
        // TEST 7: Mnożenie przez zero (0.0 * 5.0 = 0.0)
        // ================================================================
        $display("\n=== TEST 7: Mnożenie przez zero (0.0 * 5.0 = 0.0) ===");
        $display("  arg1 (0.0): E=0, M=0 (specjalny wzorzec zera)");
        $display("  arg2 (5.0): S=0, E=BIAS+2, M=0.25");
        reset_module();
        write_arg1(make_fp(1'b0, 27'd0, 36'h0));
        write_arg2(make_fp(1'b0, BIAS+2, 36'h4000000));
        start_operation();
        read_result(result_val);
        display_fp(result_val, "  Wynik ");
        $display("  Oczekiwany: 0.0");
        $display("  TEST 7: %s",
        (result_val == 64'h0) ? "ZALICZONY" : "BLAD");

        // ================================================================
        // TEST 8: -2.0 * -3.0 = +6.0
        // ================================================================
        $display("\n=== TEST 8: -2.0 * -3.0 = +6.0 ===");
        $display("  arg1 (-2.0): S=1, E=BIAS+1, M=0");
        $display("  arg2 (-3.0): S=1, E=BIAS+1, M=0.5");
        reset_module();
        write_arg1(make_fp(1'b1, BIAS+1, 36'h0));
        write_arg2(make_fp(1'b1, BIAS+1, 36'h80000000));
        start_operation();
        read_result(result_val);
        display_fp(result_val, "  Wynik ");
        $display("  Oczekiwany: S=0, E=BIAS+2, M=0.5");
        $display("  TEST 8: %s",
        (result_val[0] == 0 && result_val[63:28] == 36'h80000000)
        ? "ZALICZONY" : "BLAD");

        // ================================================================
        // TEST 9: Odczyt przed zakonczeniem operacji
        // ================================================================
        $display("\n=== TEST 9: Odczyt przed zakonczeniem ===");
        reset_module();
        write_arg1(make_fp(1'b0, BIAS, 36'h0));
        write_arg2(make_fp(1'b0, BIAS+1, 36'h0));
        
        // Uruchom, ale NIE czekaj długo
        #10 saddress = 16'h00D0; sdata_in = 32'h1; swr = 1; #10 swr = 0;
        #10; // Tylko jeden cykl
        
        read_status(status_val);
        $display("  Status po 1 cyklu: %h (0=IDLE, 1=BUSY, 2=DONE)", status_val);
        
        read_result(result_val);
        display_fp(result_val, "  Przedwczesny odczyt");
        
        // Poczekaj na zakonczenie
        #50;
        read_status(status_val);
        $display("  Status po odczekaniu: %h (oczekiwane: 2=DONE)", status_val);
        read_result(result_val);
        display_fp(result_val, "  Wynik po odczekaniu");
        $display("  TEST 9: %s",
        (result_val[0] == 0 && result_val[27:1] == BIAS+1 && result_val[63:28] == 0)
        ? "ZALICZONY" : "BLAD");

        // ================================================================
        // TEST 10: Podwójny start
        // ================================================================
        $display("\n=== TEST 10: Podwójny start ===");
        reset_module();
        write_arg1(make_fp(1'b0, BIAS, 36'h0));
        write_arg2(make_fp(1'b0, BIAS+1, 36'h0));
        
        // Pierwszy start
        #10 saddress = 16'h00D0; sdata_in = 32'h1; swr = 1; #10 swr = 0;
        #10;
        
        // Drugi start (przed zakonczeniem)
        #10 saddress = 16'h00D0; sdata_in = 32'h1; swr = 1; #10 swr = 0;
        #50;
        read_result(result_val);
        display_fp(result_val, "  Wynik po podwojnym starcie");
        $display("  TEST 10: %s",
        (result_val[0] == 0 && result_val[27:1] == BIAS+1 && result_val[63:28] == 0)
        ? "ZALICZONY" : "BLAD");

        // ================================================================
        // TEST 11: Nieprawidłowe wartości control
        // ================================================================
        $display("\n=== TEST 11: Nieprawidlowe wartosci control ===");
        reset_module();
        write_arg1(make_fp(1'b0, BIAS, 36'h0));
        write_arg2(make_fp(1'b0, BIAS+1, 36'h0));
        
        // control = 0xFF
        #10 saddress = 16'h00D0; sdata_in = 32'h000000FF; swr = 1; #10 swr = 0;
        #30;
        read_status(status_val);
        $display("  Status po control=0xFF: %h (oczekiwane: 0=IDLE)", status_val);
        $display("  TEST 11a: %s", (status_val == 32'h0) ? "ZALICZONY" : "BLAD");
        
        // control = 2
        #10 saddress = 16'h00D0; sdata_in = 32'h00000002; swr = 1; #10 swr = 0;
        #30;
        read_status(status_val);
        $display("  Status po control=2: %h (oczekiwane: 0=IDLE)", status_val);
        $display("  TEST 11b: %s", (status_val == 32'h0) ? "ZALICZONY" : "BLAD");

        // ================================================================
        // TEST 12: Częściowy zapis argumentów
        // ================================================================
        $display("\n=== TEST 12: Czesciowy zapis argumentow ===");
        reset_module();
        
        // Zapisz tylko górną część arg1
        #10 saddress = 16'h0100; sdata_in = 32'h80000000; swr = 1; #10 swr = 0;
        
        // Dolna część powinna być 0 (z resetu)
        #10 saddress = 16'h0108; srd = 1; #10 srd = 0;
        $display("  arg1_l po czesciowym zapisie: %h (oczekiwane: 00000000)", sdata_out);
        $display("  TEST 12: %s", (sdata_out == 32'h0) ? "ZALICZONY" : "BLAD");

        // ================================================================
        // TEST 13: Przemienność mnożenia (a*b == b*a)
        // ================================================================
        $display("\n=== TEST 13: Przemiennosc mnozenia ===");
        
        // 2.0 * 1.0
        reset_module();
        write_arg1(make_fp(1'b0, BIAS+1, 36'h0));  // 2.0
        write_arg2(make_fp(1'b0, BIAS, 36'h0));    // 1.0
        start_operation();
        read_result(result1);
        display_fp(result1, "  2.0*1.0");
        
        // 1.0 * 2.0
        reset_module();
        write_arg1(make_fp(1'b0, BIAS, 36'h0));    // 1.0
        write_arg2(make_fp(1'b0, BIAS+1, 36'h0));  // 2.0
        start_operation();
        read_result(result2);
        display_fp(result2, "  1.0*2.0");
        
        if (result1 == result2) begin
            $display("  Przemiennosc: OK");
            $display("  TEST 13: ZALICZONY");
        end else begin
            $display("  Przemiennosc: BLAD! (%h != %h)", result1, result2);
            $display("  TEST 13: BLAD");
        end

        // ================================================================
        // TEST 14: Próba zapisu do rejestru tylko do odczytu (status)
        // ================================================================
        $display("\n=== TEST 14: Zapis do rejestru status (read-only) ===");
        reset_module();
        #10 saddress = 16'h00E8; sdata_in = 32'hFFFFFFFF; swr = 1; #10 swr = 0;
        #10 saddress = 16'h00E8; srd = 1; #10 srd = 0;
        $display("  Status po próbie zapisu: %h (oczekiwane: 0)", sdata_out);
        $display("  TEST 14: %s", (sdata_out == 32'h0) ? "ZALICZONY" : "BLAD");

        // ================================================================
        // TEST 15: Wielokrotne mnożenie bez resetu
        // ================================================================
        $display("\n=== TEST 15: Wielokrotne mnozenie ===");
        reset_module();
        
        // Pierwsza operacja: 1.0 * 2.0 = 2.0
        write_arg1(make_fp(1'b0, BIAS, 36'h0));
        write_arg2(make_fp(1'b0, BIAS+1, 36'h0));
        start_operation();
        read_result(result1);
        display_fp(result1, "  Operacja 1 (1.0*2.0)");
        
        // Druga operacja: 2.0 * 4.0 = 8.0
        write_arg1(make_fp(1'b0, BIAS+1, 36'h0));  // 2.0
        write_arg2(make_fp(1'b0, BIAS+2, 36'h0));  // 4.0
        start_operation();
        read_result(result2);
        display_fp(result2, "  Operacja 2 (2.0*4.0)");
        $display("  Oczekiwany: S=0, E=BIAS+3, M=0");
        $display("  TEST 15: %s",
        (result2[0] == 0 && result2[27:1] == BIAS+3 && result2[63:28] == 0) 
        ? "ZALICZONY" : "BLAD");

        // Koniec symulacji
        #100;
        $display("\n===========================================");
        $display("=== WSZYSTKIE TESTY ZAKONCZONE ===");
        $display("===========================================\n");
        $finish;
    end

    // Monitor komunikatów (uproszczony)
    initial begin
        $monitor("Czas=%0t | Adr=%h | swr=%b srd=%b | data_in=%h | data_out=%h",
        $time, saddress, swr, srd, sdata_in, sdata_out);
    end
endmodule

Projekt/gpioemu.vcd
$date
	Wed Apr 29 13:10:32 2026
$end
$version
	Icarus Verilog
$end
$timescale
	1s
$end
$scope module gpioemu_tb $end
$var wire 32 ! sdata_out [31:0] $end
$var wire 32 " gpio_out [31:0] $end
$var wire 32 # gpio_in_s_insp [31:0] $end
$var parameter 27 $ BIAS $end
$var reg 1 % clk $end
$var reg 32 & gpio_in [31:0] $end
$var reg 1 ' gpio_latch $end
$var reg 1 ( n_reset $end
$var reg 64 ) result1 [63:0] $end
$var reg 64 * result2 [63:0] $end
$var reg 64 + result_val [63:0] $end
$var reg 16 , saddress [15:0] $end
$var reg 32 - sdata_in [31:0] $end
$var reg 1 . srd $end
$var reg 32 / status_val [31:0] $end
$var reg 1 0 swr $end
$scope function make_fp $end
$var reg 27 1 e [26:0] $end
$var reg 36 2 m [35:0] $end
$var reg 1 3 s $end
$upscope $end
$scope module test_module $end
$var wire 1 4 arg1_is_zero $end
$var wire 1 5 arg2_is_zero $end
$var wire 1 % clk $end
$var wire 32 6 gpio_in [31:0] $end
$var wire 32 7 gpio_in_s_insp [31:0] $end
$var wire 1 ' gpio_latch $end
$var wire 32 8 gpio_out [31:0] $end
$var wire 1 ( n_reset $end
$var wire 16 9 saddress [15:0] $end
$var wire 32 : sdata_in [31:0] $end
$var wire 1 . srd $end
$var wire 1 0 swr $end
$var wire 74 ; mant2_ext [73:0] $end
$var wire 74 < mant1_ext [73:0] $end
$var parameter 27 = BIAS $end
$var parameter 2 > CALC $end
$var parameter 2 ? DONE $end
$var parameter 2 @ IDLE $end
$var reg 64 A arg1 [63:0] $end
$var reg 64 B arg2 [63:0] $end
$var reg 1 C ena $end
$var reg 28 D exp_sum [27:0] $end
$var reg 32 E gpio_in_s [31:0] $end
$var reg 32 F gpio_out_s [31:0] $end
$var reg 74 G mant_prod [73:0] $end
$var reg 64 H result [63:0] $end
$var reg 32 I sdata_in_s [31:0] $end
$var reg 32 J sdata_out [31:0] $end
$var reg 1 K sign_r $end
$var reg 2 L state [1:0] $end
$var reg 32 M status [31:0] $end
$upscope $end
$scope task display_fp $end
$var reg 27 N exp [26:0] $end
$var reg 64 O fp [63:0] $end
$var reg 256 P label [255:0] $end
$var reg 36 Q mant [35:0] $end
$var reg 1 R sign $end
$upscope $end
$scope task read_result $end
$var reg 64 S result [63:0] $end
$upscope $end
$scope task read_status $end
$var reg 32 T stat [31:0] $end
$upscope $end
$scope task reset_module $end
$upscope $end
$scope task start_operation $end
$upscope $end
$scope task write_arg1 $end
$var reg 64 U value [63:0] $end
$upscope $end
$scope task write_arg2 $end
$var reg 64 V value [63:0] $end
$upscope $end
$upscope $end
$enddefinitions $end
$comment Show the parameter values. $end
$dumpall
b0 @
b10 ?
b1 >
b100000000000000000000000000 =
b100000000000000000000000000 $
$end
#0
$dumpvars
bx V
bx U
bx T
bx S
xR
bx Q
bx P
bx O
bx N
bx M
bx L
xK
bx J
b0 I
bx H
bx G
bx F
bx E
bx D
xC
bx B
bx A
b0xxxxxxxxxxxxxxxxxxxxxxxxxxxxxxxxxxxxx <
b0xxxxxxxxxxxxxxxxxxxxxxxxxxxxxxxxxxxxx ;
b0 :
b0 9
bx 8
bx 7
b0 6
x5
x4
x3
bx 2
bx 1
00
b0 /
0.
b0 -
b0 ,
b0 +
b0 *
b0 )
1(
0'
b0 &
0%
bx #
bx "
bx !
$end
#5
b0 M
b0 L
1%
#10
15
b0 ;
14
b0 <
b0 !
b0 J
b0 H
0C
b0 B
b0 A
b0 #
b0 7
b0 E
0%
0(
#15
1%
#20
0%
1(
#25
1%
#30
0%
b1000000000000000000000000000 U
03
b100000000000000000000000000 1
b0 2
#35
1%
#40
0%
10
b100000000 ,
b100000000 9
#45
1%
#50
0%
00
#55
1%
#60
b1000000000000000000000000000000000000 <
04
b1000000000000000000000000000 A
b1000000000000000000000000000 I
0%
10
b1000000000000000000000000000 -
b1000000000000000000000000000 :
b100001000 ,
b100001000 9
#65
1%
#70
0%
b1000000000000000000000000010 V
b100000000000000000000000001 1
00
#75
1%
#80
b0 I
0%
10
b0 -
b0 :
b11110000 ,
b11110000 9
#85
1%
#90
0%
00
#95
1%
#100
b1000000000000000000000000000000000000 ;
05
b1000000000000000000000000010 B
b1000000000000000000000000010 I
0%
10
b1000000000000000000000000010 -
b1000000000000000000000000010 :
b11111000 ,
b11111000 9
#105
1%
#110
0%
00
#115
1%
#120
1C
b1 I
0%
10
b1 -
b1 :
b11010000 ,
b11010000 9
#125
b1 L
1%
#130
0%
00
#135
b10 L
bx H
0K
b100000000000000000000000001 D
b1000000000000000000000000000000000000000000000000000000000000000000000000 G
b1 M
1%
#140
0%
#145
b10 M
1%
#150
0%
#155
1%
#160
0%
#165
1%
#170
0%
#175
1%
#180
0%
#185
1%
#190
b10 !
b10 J
0%
1.
b11101000 ,
b11101000 9
#195
1%
#200
0%
b10 /
b10 T
0.
#205
1%
#210
bx !
bx J
0%
1.
b11011000 ,
b11011000 9
#215
1%
#220
0%
0.
#225
1%
#230
0%
1.
b11100000 ,
b11100000 9
#235
1%
#240
0%
b10000000100000010101110111100101101110011010010110101100100000 P
bx +
0.
#245
1%
#250
b0 ;
b0 <
15
14
b0 !
b0 J
b0 H
b0 M
b0 L
0C
b0 B
b0 A
0%
0(
#255
1%
#260
0%
1(
#265
1%
#270
0%
b100000000000000000000000000000001000000000000000000000000001 U
13
b100000000000000000000000000 1
b10000000000000000000000000000000 2
#275
1%
#280
b1000010000000000000000000000000000000 <
04
b100000000000000000000000000000000000000000000000000000000000 A
b1000000000000000000000000000 I
0%
10
b1000000000000000000000000000 -
b1000000000000000000000000000 :
b100000000 ,
b100000000 9
#285
1%
#290
0%
00
#295
1%
#300
b100000000000000000000000000000001000000000000000000000000001 A
b1000000000000000000000000001 I
0%
10
b1000000000000000000000000001 -
b1000000000000000000000000001 :
b100001000 ,
b100001000 9
#305
1%
#310
0%
03
b100000000000000000000000001 1
b0 2
00
#315
1%
#320
b0 I
0%
10
b0 -
b0 :
b11110000 ,
b11110000 9
#325
1%
#330
0%
00
#335
1%
#340
b1000000000000000000000000000000000000 ;
05
b1000000000000000000000000010 B
b1000000000000000000000000010 I
0%
10
b1000000000000000000000000010 -
b1000000000000000000000000010 :
b11111000 ,
b11111000 9
#345
1%
#350
0%
00
#355
1%
#360
1C
b1 I
0%
10
b1 -
b1 :
b11010000 ,
b11010000 9
#365
b1 L
1%
#370
0%
00
#375
b10 L
b1000000000000000000000000010 H
1K
b1000010000000000000000000000000000000000000000000000000000000000000000000 G
b1 M
1%
#380
0%
#385
b10 M
1%
#390
0%
#395
1%
#400
0%
#405
1%
#410
0%
#415
1%
#420
0%
#425
1%
#430
0%
1.
b11011000 ,
b11011000 9
#435
1%
#440
0%
b0xxxxxxxxxxxxxxxxxxxxxxxxxxxxxxxx S
0.
#445
1%
#450
b1000000000000000000000000010 !
b1000000000000000000000000010 J
0%
1.
b11100000 ,
b11100000 9
#455
1%
#460
0%
b0 Q
b100000000000000000000000001 N
0R
b1000000000000000000000000010 O
b1000000000000000000000000010 +
b1000000000000000000000000010 S
0.
#465
1%
#470
b0 !
b0 J
0%
1.
b1111111111111111 ,
b1111111111111111 9
#475
1%
#480
0%
0.
#485
1%
#490
b0 ;
15
14
b0 <
b0 H
b0 M
b0 L
0C
b0 B
b0 A
0%
0(
#495
1%
#500
0%
1(
#505
1%
#510
0%
b1000000000000000000000000000 U
b100000000000000000000000000 1
#515
1%
#520
b0 I
0%
10
b0 -
b0 :
b100000000 ,
b100000000 9
#525
1%
#530
0%
00
#535
1%
#540
b1000000000000000000000000000000000000 <
04
b1000000000000000000000000000 A
b1000000000000000000000000000 I
0%
10
b1000000000000000000000000000 -
b1000000000000000000000000000 :
b100001000 ,
b100001000 9
#545
1%
#550
0%
b100000000000000000000000001 1
00
#555
1%
#560
b0 I
0%
10
b0 -
b0 :
b11110000 ,
b11110000 9
#565
1%
#570
0%
00
#575
1%
#580
b1000000000000000000000000000000000000 ;
05
b1000000000000000000000000010 B
b1000000000000000000000000010 I
0%
10
b1000000000000000000000000010 -
b1000000000000000000000000010 :
b11111000 ,
b11111000 9
#585
1%
#590
0%
00
#595
1%
#600
b0 I
0%
10
b0 -
b0 :
b11010000 ,
b11010000 9
#605
1%
#610
0%
00
#615
1%
#620
0%
#625
1%
#630
0%
#635
1%
#640
0%
1.
b11101000 ,
b11101000 9
#645
1%
#650
0%
b0 /
b0 T
0.
#655
1%
#660
0%
b11011110101011011011111011101111 &
b11011110101011011011111011101111 6
#665
1%
#670
b11011110101011011011111011101111 #
b11011110101011011011111011101111 7
b11011110101011011011111011101111 E
0%
1'
#675
1%
#680
0%
0'
#685
1%
#690
0%
#695
1%
#700
b0 ;
b0 <
15
14
b0 B
b0 A
b0 #
b0 7
b0 E
0%
0(
#705
1%
#710
0%
1(
#715
1%
#720
0%
#725
1%
#730
0%
1.
b100000000 ,
b100000000 9
#735
1%
#740
0%
0.
#745
1%
#750
0%
0(
#755
1%
#760
0%
1(
#765
1%
#770
0%
b0 U
b0 1
#775
1%
#780
0%
10
#785
1%
#790
0%
00
#795
1%
#800
0%
10
b100001000 ,
b100001000 9
#805
1%
#810
0%
b1000000000000000000000000001000000000000000000000000100 V
b100000000000000000000000010 1
b100000000000000000000000000 2
00
#815
1%
#820
b1000000000100000000000000000000000000 ;
05
b1000000000000000000000000000000000000000000000000000000 B
b10000000000000000000000 I
0%
10
b10000000000000000000000 -
b10000000000000000000000 :
b11110000 ,
b11110000 9
#825
1%
#830
0%
00
#835
1%
#840
b1000000000000000000000000001000000000000000000000000100 B
b1000000000000000000000000100 I
0%
10
b1000000000000000000000000100 -
b1000000000000000000000000100 :
b11111000 ,
b11111000 9
#845
1%
#850
0%
00
#855
1%
#860
1C
b1 I
0%
10
b1 -
b1 :
b11010000 ,
b11010000 9
#865
b1 L
1%
#870
0%
00
#875
b10 L
0K
b10 D
b0 G
b1 M
1%
#880
0%
#885
b10 M
1%
#890
0%
#895
1%
#900
0%
#905
1%
#910
0%
#915
1%
#920
0%
#925
1%
#930
0%
1.
b11011000 ,
b11011000 9
#935
1%
#940
0%
0.
#945
1%
#950
0%
1.
b11100000 ,
b11100000 9
#955
1%
#960
0%
b0 N
b0 O
b0 +
b0 S
0.
#965
1%
#970
15
b0 ;
b0 M
b0 L
0C
b0 B
0%
0(
#975
1%
#980
0%
1(
#985
1%
#990
0%
b1000000000000000000000000011 U
13
b100000000000000000000000001 1
b0 2
#995
1%
#1000
b0 I
0%
10
b0 -
b0 :
b100000000 ,
b100000000 9
#1005
1%
#1010
0%
00
#1015
1%
#1020
b1000000000000000000000000000000000000 <
04
b1000000000000000000000000011 A
b1000000000000000000000000011 I
0%
10
b1000000000000000000000000011 -
b1000000000000000000000000011 :
b100001000 ,
b100001000 9
#1025
1%
#1030
0%
b100000000000000000000000000000001000000000000000000000000011 V
b10000000000000000000000000000000 2
00
#1035
1%
#1040
b1000010000000000000000000000000000000 ;
05
b100000000000000000000000000000000000000000000000000000000000 B
b1000000000000000000000000000 I
0%
10
b1000000000000000000000000000 -
b1000000000000000000000000000 :
b11110000 ,
b11110000 9
#1045
1%
#1050
0%
00
#1055
1%
